{
    "DNDConfig": null,
    "_height_": {
        "type": "string",
        "value": "30dp"
    },
    "_left_": {
        "type": "string",
        "value": "0dp"
    },
    "_margin_": [
        0,
        0,
        0,
        0
    ],
    "_orientation_": 6,
    "_padding_": [
        0,
        0,
        0,
        0
    ],
    "_percent_": true,
    "_skin_": "s7b436962d6a4647b197083ac7d03d38",
    "_top_": {
        "type": "string",
        "value": "0dp"
    },
    "_width_": {
        "type": "string",
        "value": "100%"
    },
    "allboxes": [],
    "autogrowmode": 0,
    "canUpdateUI": true,
    "children": [
        "flxDetailFour",
        "flxDetailFive"
    ],
    "clipbounds": true,
    "containerId": true,
    "containerweight": 100,
    "disabledSkins": {},
    "enablescrolling": true,
    "focusskin": "s7b436962d6a4647b197083ac7d03d38",
    "id": "flxRowFour",
    "info": null,
    "iscustomlayout": false,
    "isvisible": true,
    "kuid": "bcf9f48d0d1f429baf31a49538af60ce",
    "layouttype": 3,
    "name": "kony.ui.FlexContainer",
    "parent": "flxMain",
    "pf": "segWealthDetails",
    "retaincontentalignment": false,
    "retainflexpositionproperties": false,
    "retainflowhorizontalalignment": false,
    "snapgridsize": 10,
    "snaptogrid": true,
    "wType": "FlexContainer",
    "widgetalignment": 1,
    "zindex": 1
}