{
  "customCode" : {
    "requestProcessorName" : "com.kony.dbputilities.mfa.preprocessors.ACHTransactionsMFAPreProcessor"
  },
  "operationConfig" : {
    "name" : "createTransaction2519",
    "type" : "MappedToBackend",
    "cachable" : false,
    "smsEnabled" : false,
    "security" : "authorized_app_user",
    "responseEncoding" : "UTF-8",
    "httpMethod" : "GET",
    "decodeResponseBody" : false,
    "iMapping" : "<?xml version=\"1.0\" encoding=\"UTF-8\" standalone=\"yes\"?><mapper xmlns=\"http://www.kony.com/ns/mapper\">              <map inputpath=\"request_in\" outputpath=\"request_out\">                            <set-param inputpath=\"ConfirmationNumber\" outputpath=\"ConfirmationNumber\"/>                            <set-param inputpath=\"DebitAccount\" outputpath=\"DebitAccount\"/>                            <set-param inputpath=\"EffectiveDate\" outputpath=\"EffectiveDate\"/>                            <set-param inputpath=\"MaxAmount\" outputpath=\"MaxAmount\"/>                            <set-param inputpath=\"TotalAmount\" outputpath=\"TotalAmount\" />                            <set-param inputpath=\"Records\" outputpath=\"Records\"/>                            <set-param inputpath=\"TemplateRequestType_id\" outputpath=\"TemplateRequestType_id\"/>            <set-param inputpath=\"TemplateRequestTypeValue\" outputpath=\"TemplateRequestTypeValue\"/>            <set-param inputpath=\"TemplateType_id\" outputpath=\"TemplateType_id\"/>                            <set-param inputpath=\"TransactionType_id\" outputpath=\"TransactionType_id\"/>         <set-param inputpath=\"transactionId\" outputpath=\"transactionId\"/>    <set-param inputpath=\"transactionAmount\" outputpath=\"transactionAmount\"/>    <set-param inputpath=\"transactionCurrency\" outputpath=\"transactionCurrency\"/>    <set-param inputpath=\"serviceCharge\" outputpath=\"serviceCharge\"/>  </map></mapper>",
    "oMapping" : "<?xml version=\"1.0\" encoding=\"UTF-8\" standalone=\"yes\"?><mapper xmlns=\"http://www.kony.com/ns/mapper\">      <map inputpath=\"response_in\" outputpath=\"response_out\">              <set-param inputpath=\"transaction_id\" outputpath=\"Transaction_id\"/>              <set-param inputpath=\"referenceId\" outputpath=\"ReferenceID\"/>              <set-param inputpath=\"status\" outputpath=\"Status\"/>              <set-param inputpath=\"dbpErrCode\" outputpath=\"dbpErrCode\"/>              <set-param inputpath=\"dbpErrMsg\" outputpath=\"dbpErrMsg\"/>              <set-param inputpath=\"opstatus\" outputpath=\"opstatus\"/>              <set-param inputpath=\"httpStatusCode\" outputpath=\"httpStatusCode\"/>              <set-param inputpath=\"requestId\" outputpath=\"requestId\"/>     <set-param inputpath=\"totalAmount\" outputpath=\"totalAmount\"/>     <set-param inputpath=\"transactionAmount\" outputpath=\"transactionAmount\"/>            <set-param inputpath=\"transactionCurrency\" outputpath=\"transactionCurrency\"/>            <set-param inputpath=\"serviceCharge\" outputpath=\"serviceCharge\"/>     </map></mapper>",
    "iVisualMappingData" : "{\"nodeDataArray\":[{\"isGroup\":true,\"key\":\"request_in\",\"text\":\"ACHTransactions\",\"xy\":\"-36.46452443824228 31.360712899374988\"},{\"isGroup\":true,\"key\":\"request_out\",\"text\":\"dbpACHServices (1.0).createTransaction\",\"xy\":\"1074.3558214205468 76.36071289937499\"}],\"linkDataArray\":[{\"category\":\"Mapping\",\"visible\":true,\"from\":\"source:ACHTransactions:TemplateRequestType_id:\",\"to\":\"target:TemplateRequestType_id:\",\"fromPort\":\"source:ACHTransactions:TemplateRequestType_id:\",\"toPort\":\"target:TemplateRequestType_id:\"},{\"category\":\"Mapping\",\"visible\":true,\"from\":\"source:ACHTransactions:TemplateType_id:\",\"to\":\"target:TemplateType_id:\",\"fromPort\":\"source:ACHTransactions:TemplateType_id:\",\"toPort\":\"target:TemplateType_id:\"},{\"category\":\"Mapping\",\"visible\":true,\"from\":\"source:ACHTransactions:TransactionType_id:\",\"to\":\"target:TransactionType_id:\",\"fromPort\":\"source:ACHTransactions:TransactionType_id:\",\"toPort\":\"target:TransactionType_id:\"},{\"category\":\"Mapping\",\"visible\":true,\"from\":\"source:ACHTransactions:MaxAmount:\",\"to\":\"target:MaxAmount:\",\"fromPort\":\"source:ACHTransactions:MaxAmount:\",\"toPort\":\"target:MaxAmount:\"},{\"category\":\"Mapping\",\"visible\":true,\"from\":\"source:ACHTransactions:EffectiveDate:\",\"to\":\"target:EffectiveDate:\",\"fromPort\":\"source:ACHTransactions:EffectiveDate:\",\"toPort\":\"target:EffectiveDate:\"},{\"category\":\"Mapping\",\"visible\":true,\"from\":\"source:ACHTransactions:ConfirmationNumber:\",\"to\":\"target:ConfirmationNumber:\",\"fromPort\":\"source:ACHTransactions:ConfirmationNumber:\",\"toPort\":\"target:ConfirmationNumber:\"},{\"category\":\"Mapping\",\"visible\":true,\"from\":\"source:ACHTransactions:DebitAccount:\",\"to\":\"target:DebitAccount:\",\"fromPort\":\"source:ACHTransactions:DebitAccount:\",\"toPort\":\"target:DebitAccount:\"},{\"category\":\"Mapping\",\"visible\":true,\"from\":\"source:ACHTransactions:Records:\",\"to\":\"target:Records:\",\"fromPort\":\"source:ACHTransactions:Records:\",\"toPort\":\"target:Records:\"},{\"from\":\"source\",\"to\":\"source:ACHTransactions\",\"fromPort\":\"source\",\"toPort\":\"source:ACHTransactions\",\"visible\":true,\"common\":false},{\"from\":\"source:ACHTransactions\",\"to\":\"source:ACHTransactions:t_p_fields\",\"fromPort\":\"source:ACHTransactions\",\"toPort\":\"source:ACHTransactions:t_p_fields\",\"visible\":true,\"common\":false},{\"from\":\"source:ACHTransactions:t_p_fields\",\"to\":\"source:ACHTransactions:BBGeneralTransactionType_id:\",\"fromPort\":\"source:ACHTransactions:t_p_fields\",\"toPort\":\"source:ACHTransactions:BBGeneralTransactionType_id:\",\"visible\":true,\"common\":false},{\"from\":\"source:ACHTransactions:t_p_fields\",\"to\":\"source:ACHTransactions:Status:\",\"fromPort\":\"source:ACHTransactions:t_p_fields\",\"toPort\":\"source:ACHTransactions:Status:\",\"visible\":true,\"common\":false},{\"from\":\"source:ACHTransactions:t_p_fields\",\"to\":\"source:ACHTransactions:TemplateRequestType_id:\",\"fromPort\":\"source:ACHTransactions:t_p_fields\",\"toPort\":\"source:ACHTransactions:TemplateRequestType_id:\",\"visible\":true,\"common\":false},{\"from\":\"source:ACHTransactions:t_p_fields\",\"to\":\"source:ACHTransactions:Request_id:\",\"fromPort\":\"source:ACHTransactions:t_p_fields\",\"toPort\":\"source:ACHTransactions:Request_id:\",\"visible\":true,\"common\":false},{\"from\":\"source:ACHTransactions:t_p_fields\",\"to\":\"source:ACHTransactions:userName:\",\"fromPort\":\"source:ACHTransactions:t_p_fields\",\"toPort\":\"source:ACHTransactions:userName:\",\"visible\":true,\"common\":false},{\"from\":\"source:ACHTransactions:t_p_fields\",\"to\":\"source:ACHTransactions:DebitAccount:\",\"fromPort\":\"source:ACHTransactions:t_p_fields\",\"toPort\":\"source:ACHTransactions:DebitAccount:\",\"visible\":true,\"common\":false},{\"from\":\"source:ACHTransactions:t_p_fields\",\"to\":\"source:ACHTransactions:CreatedOn:\",\"fromPort\":\"source:ACHTransactions:t_p_fields\",\"toPort\":\"source:ACHTransactions:CreatedOn:\",\"visible\":true,\"common\":false},{\"from\":\"source:ACHTransactions:t_p_fields\",\"to\":\"source:ACHTransactions:MaxAmount:\",\"fromPort\":\"source:ACHTransactions:t_p_fields\",\"toPort\":\"source:ACHTransactions:MaxAmount:\",\"visible\":true,\"common\":false},{\"from\":\"source:ACHTransactions:t_p_fields\",\"to\":\"source:ACHTransactions:TemplateType_id:\",\"fromPort\":\"source:ACHTransactions:t_p_fields\",\"toPort\":\"source:ACHTransactions:TemplateType_id:\",\"visible\":true,\"common\":false},{\"from\":\"source:ACHTransactions:t_p_fields\",\"to\":\"source:ACHTransactions:CompanyName:\",\"fromPort\":\"source:ACHTransactions:t_p_fields\",\"toPort\":\"source:ACHTransactions:CompanyName:\",\"visible\":true,\"common\":false},{\"from\":\"source:ACHTransactions:t_p_fields\",\"to\":\"source:ACHTransactions:RequestType:\",\"fromPort\":\"source:ACHTransactions:t_p_fields\",\"toPort\":\"source:ACHTransactions:RequestType:\",\"visible\":true,\"common\":false},{\"from\":\"source:ACHTransactions:t_p_fields\",\"to\":\"source:ACHTransactions:TemplateTypeValue:\",\"fromPort\":\"source:ACHTransactions:t_p_fields\",\"toPort\":\"source:ACHTransactions:TemplateTypeValue:\",\"visible\":true,\"common\":false},{\"from\":\"source:ACHTransactions:t_p_fields\",\"to\":\"source:ACHTransactions:softDelete:\",\"fromPort\":\"source:ACHTransactions:t_p_fields\",\"toPort\":\"source:ACHTransactions:softDelete:\",\"visible\":true,\"common\":false},{\"from\":\"source:ACHTransactions:t_p_fields\",\"to\":\"source:ACHTransactions:TransactionType_id:\",\"fromPort\":\"source:ACHTransactions:t_p_fields\",\"toPort\":\"source:ACHTransactions:TransactionType_id:\",\"visible\":true,\"common\":false},{\"from\":\"source:ACHTransactions:t_p_fields\",\"to\":\"source:ACHTransactions:CreatedBy:\",\"fromPort\":\"source:ACHTransactions:t_p_fields\",\"toPort\":\"source:ACHTransactions:CreatedBy:\",\"visible\":true,\"common\":false},{\"from\":\"source:ACHTransactions:t_p_fields\",\"to\":\"source:ACHTransactions:Company_id:\",\"fromPort\":\"source:ACHTransactions:t_p_fields\",\"toPort\":\"source:ACHTransactions:Company_id:\",\"visible\":true,\"common\":false},{\"from\":\"source:ACHTransactions:t_p_fields\",\"to\":\"source:ACHTransactions:TransactionTypeValue:\",\"fromPort\":\"source:ACHTransactions:t_p_fields\",\"toPort\":\"source:ACHTransactions:TransactionTypeValue:\",\"visible\":true,\"common\":false},{\"from\":\"source:ACHTransactions:t_p_fields\",\"to\":\"source:ACHTransactions:StatusValue:\",\"fromPort\":\"source:ACHTransactions:t_p_fields\",\"toPort\":\"source:ACHTransactions:StatusValue:\",\"visible\":true,\"common\":false},{\"from\":\"source:ACHTransactions:t_p_fields\",\"to\":\"source:ACHTransactions:Transaction_id:\",\"fromPort\":\"source:ACHTransactions:t_p_fields\",\"toPort\":\"source:ACHTransactions:Transaction_id:\",\"visible\":true,\"common\":false},{\"from\":\"source:ACHTransactions:t_p_fields\",\"to\":\"source:ACHTransactions:EffectiveDate:\",\"fromPort\":\"source:ACHTransactions:t_p_fields\",\"toPort\":\"source:ACHTransactions:EffectiveDate:\",\"visible\":true,\"common\":false},{\"from\":\"source:ACHTransactions:t_p_fields\",\"to\":\"source:ACHTransactions:TemplateName:\",\"fromPort\":\"source:ACHTransactions:t_p_fields\",\"toPort\":\"source:ACHTransactions:TemplateName:\",\"visible\":true,\"common\":false},{\"from\":\"source:ACHTransactions:t_p_fields\",\"to\":\"source:ACHTransactions:ConfirmationNumber:\",\"fromPort\":\"source:ACHTransactions:t_p_fields\",\"toPort\":\"source:ACHTransactions:ConfirmationNumber:\",\"visible\":true,\"common\":false},{\"from\":\"source:ACHTransactions:t_p_fields\",\"to\":\"source:ACHTransactions:Approver:\",\"fromPort\":\"source:ACHTransactions:t_p_fields\",\"toPort\":\"source:ACHTransactions:Approver:\",\"visible\":true,\"common\":false},{\"from\":\"source:ACHTransactions:t_p_fields\",\"to\":\"source:ACHTransactions:Records:\",\"fromPort\":\"source:ACHTransactions:t_p_fields\",\"toPort\":\"source:ACHTransactions:Records:\",\"visible\":true,\"common\":false},{\"from\":\"source:ACHTransactions:t_p_fields\",\"to\":\"source:ACHTransactions:TemplateDescription:\",\"fromPort\":\"source:ACHTransactions:t_p_fields\",\"toPort\":\"source:ACHTransactions:TemplateDescription:\",\"visible\":true,\"common\":false},{\"from\":\"source:ACHTransactions:t_p_fields\",\"to\":\"source:ACHTransactions:TotalAmount:\",\"fromPort\":\"source:ACHTransactions:t_p_fields\",\"toPort\":\"source:ACHTransactions:TotalAmount:\",\"visible\":true,\"common\":false},{\"from\":\"source:ACHTransactions:t_p_fields\",\"to\":\"source:ACHTransactions:ReferenceID:\",\"fromPort\":\"source:ACHTransactions:t_p_fields\",\"toPort\":\"source:ACHTransactions:ReferenceID:\",\"visible\":true,\"common\":false},{\"from\":\"source:ACHTransactions:t_p_fields\",\"to\":\"source:ACHTransactions:opstatus:\",\"fromPort\":\"source:ACHTransactions:t_p_fields\",\"toPort\":\"source:ACHTransactions:opstatus:\",\"visible\":true,\"common\":false},{\"from\":\"source:ACHTransactions:t_p_fields\",\"to\":\"source:ACHTransactions:httpStatusCode:\",\"fromPort\":\"source:ACHTransactions:t_p_fields\",\"toPort\":\"source:ACHTransactions:httpStatusCode:\",\"visible\":true,\"common\":false},{\"from\":\"source:ACHTransactions:t_p_fields\",\"to\":\"source:ACHTransactions:dbpErrCode:\",\"fromPort\":\"source:ACHTransactions:t_p_fields\",\"toPort\":\"source:ACHTransactions:dbpErrCode:\",\"visible\":true,\"common\":false},{\"from\":\"source:ACHTransactions:t_p_fields\",\"to\":\"source:ACHTransactions:dbpErrMsg:\",\"fromPort\":\"source:ACHTransactions:t_p_fields\",\"toPort\":\"source:ACHTransactions:dbpErrMsg:\",\"visible\":true,\"common\":false},{\"from\":\"source:ACHTransactions:t_p_fields\",\"to\":\"source:ACHTransactions:featureActionId:\",\"fromPort\":\"source:ACHTransactions:t_p_fields\",\"toPort\":\"source:ACHTransactions:featureActionId:\",\"visible\":true,\"common\":false},{\"from\":\"source:ACHTransactions:t_p_fields\",\"to\":\"source:ACHTransactions:queryType:\",\"fromPort\":\"source:ACHTransactions:t_p_fields\",\"toPort\":\"source:ACHTransactions:queryType:\",\"visible\":true,\"common\":false},{\"from\":\"source:ACHTransactions:t_p_fields\",\"to\":\"source:ACHTransactions:searchString:\",\"fromPort\":\"source:ACHTransactions:t_p_fields\",\"toPort\":\"source:ACHTransactions:searchString:\",\"visible\":true,\"common\":false},{\"from\":\"source:ACHTransactions:t_p_fields\",\"to\":\"source:ACHTransactions:sortByParam:\",\"fromPort\":\"source:ACHTransactions:t_p_fields\",\"toPort\":\"source:ACHTransactions:sortByParam:\",\"visible\":true,\"common\":false},{\"from\":\"source:ACHTransactions:t_p_fields\",\"to\":\"source:ACHTransactions:sortOrder:\",\"fromPort\":\"source:ACHTransactions:t_p_fields\",\"toPort\":\"source:ACHTransactions:sortOrder:\",\"visible\":true,\"common\":false},{\"from\":\"source:ACHTransactions:t_p_fields\",\"to\":\"source:ACHTransactions:pageSize:\",\"fromPort\":\"source:ACHTransactions:t_p_fields\",\"toPort\":\"source:ACHTransactions:pageSize:\",\"visible\":true,\"common\":false},{\"from\":\"source:ACHTransactions:t_p_fields\",\"to\":\"source:ACHTransactions:pageOffset:\",\"fromPort\":\"source:ACHTransactions:t_p_fields\",\"toPort\":\"source:ACHTransactions:pageOffset:\",\"visible\":true,\"common\":false},{\"from\":\"source:ACHTransactions:t_p_fields\",\"to\":\"source:ACHTransactions:receivedApprovals:\",\"fromPort\":\"source:ACHTransactions:t_p_fields\",\"toPort\":\"source:ACHTransactions:receivedApprovals:\",\"visible\":true,\"common\":false},{\"from\":\"source:ACHTransactions:t_p_fields\",\"to\":\"source:ACHTransactions:requiredApprovals:\",\"fromPort\":\"source:ACHTransactions:t_p_fields\",\"toPort\":\"source:ACHTransactions:requiredApprovals:\",\"visible\":true,\"common\":false},{\"from\":\"source:ACHTransactions:t_p_fields\",\"to\":\"source:ACHTransactions:AccountName:\",\"fromPort\":\"source:ACHTransactions:t_p_fields\",\"toPort\":\"source:ACHTransactions:AccountName:\",\"visible\":true,\"common\":false},{\"from\":\"source:ACHTransactions:t_p_fields\",\"to\":\"source:ACHTransactions:filterByParam:\",\"fromPort\":\"source:ACHTransactions:t_p_fields\",\"toPort\":\"source:ACHTransactions:filterByParam:\",\"visible\":true,\"common\":false},{\"from\":\"source:ACHTransactions:t_p_fields\",\"to\":\"source:ACHTransactions:filterByValue:\",\"fromPort\":\"source:ACHTransactions:t_p_fields\",\"toPort\":\"source:ACHTransactions:filterByValue:\",\"visible\":true,\"common\":false},{\"from\":\"source:ACHTransactions:t_p_fields\",\"to\":\"source:ACHTransactions:amICreator:\",\"fromPort\":\"source:ACHTransactions:t_p_fields\",\"toPort\":\"source:ACHTransactions:amICreator:\",\"visible\":true,\"common\":false},{\"from\":\"source:ACHTransactions:t_p_fields\",\"to\":\"source:ACHTransactions:amIApprover:\",\"fromPort\":\"source:ACHTransactions:t_p_fields\",\"toPort\":\"source:ACHTransactions:amIApprover:\",\"visible\":true,\"common\":false},{\"from\":\"source:ACHTransactions:t_p_fields\",\"to\":\"source:ACHTransactions:TemplateRequestTypeValue:\",\"fromPort\":\"source:ACHTransactions:t_p_fields\",\"toPort\":\"source:ACHTransactions:TemplateRequestTypeValue:\",\"visible\":true,\"common\":false},{\"from\":\"source:ACHTransactions:t_p_fields\",\"to\":\"source:ACHTransactions:transactionId:\",\"fromPort\":\"source:ACHTransactions:t_p_fields\",\"toPort\":\"source:ACHTransactions:transactionId:\",\"visible\":true,\"common\":false},{\"from\":\"target\",\"to\":\"target:t_p_parameters\",\"fromPort\":\"target\",\"toPort\":\"target:t_p_parameters\",\"visible\":true,\"common\":false},{\"from\":\"target:t_p_parameters\",\"to\":\"target:ConfirmationNumber:\",\"fromPort\":\"target:t_p_parameters\",\"toPort\":\"target:ConfirmationNumber:\",\"visible\":true,\"common\":false},{\"from\":\"target:t_p_parameters\",\"to\":\"target:DebitAccount:\",\"fromPort\":\"target:t_p_parameters\",\"toPort\":\"target:DebitAccount:\",\"visible\":true,\"common\":false},{\"from\":\"target:t_p_parameters\",\"to\":\"target:EffectiveDate:\",\"fromPort\":\"target:t_p_parameters\",\"toPort\":\"target:EffectiveDate:\",\"visible\":true,\"common\":false},{\"from\":\"target:t_p_parameters\",\"to\":\"target:MaxAmount:\",\"fromPort\":\"target:t_p_parameters\",\"toPort\":\"target:MaxAmount:\",\"visible\":true,\"common\":false},{\"from\":\"target:t_p_parameters\",\"to\":\"target:Records:\",\"fromPort\":\"target:t_p_parameters\",\"toPort\":\"target:Records:\",\"visible\":true,\"common\":false},{\"from\":\"target:t_p_parameters\",\"to\":\"target:serviceCharge:\",\"fromPort\":\"target:t_p_parameters\",\"toPort\":\"target:serviceCharge:\",\"visible\":true,\"common\":false},{\"from\":\"target:t_p_parameters\",\"to\":\"target:Template_id:\",\"fromPort\":\"target:t_p_parameters\",\"toPort\":\"target:Template_id:\",\"visible\":true,\"common\":false},{\"from\":\"target:t_p_parameters\",\"to\":\"target:TemplateDescription:\",\"fromPort\":\"target:t_p_parameters\",\"toPort\":\"target:TemplateDescription:\",\"visible\":true,\"common\":false},{\"from\":\"target:t_p_parameters\",\"to\":\"target:TemplateName:\",\"fromPort\":\"target:t_p_parameters\",\"toPort\":\"target:TemplateName:\",\"visible\":true,\"common\":false},{\"from\":\"target:t_p_parameters\",\"to\":\"target:TemplateRequestType_id:\",\"fromPort\":\"target:t_p_parameters\",\"toPort\":\"target:TemplateRequestType_id:\",\"visible\":true,\"common\":false},{\"from\":\"target:t_p_parameters\",\"to\":\"target:TemplateRequestTypeValue:\",\"fromPort\":\"target:t_p_parameters\",\"toPort\":\"target:TemplateRequestTypeValue:\",\"visible\":true,\"common\":false},{\"from\":\"target:t_p_parameters\",\"to\":\"target:TemplateType_id:\",\"fromPort\":\"target:t_p_parameters\",\"toPort\":\"target:TemplateType_id:\",\"visible\":true,\"common\":false},{\"from\":\"target:t_p_parameters\",\"to\":\"target:TotalAmount:\",\"fromPort\":\"target:t_p_parameters\",\"toPort\":\"target:TotalAmount:\",\"visible\":true,\"common\":false},{\"from\":\"target:t_p_parameters\",\"to\":\"target:transactionAmount:\",\"fromPort\":\"target:t_p_parameters\",\"toPort\":\"target:transactionAmount:\",\"visible\":true,\"common\":false},{\"from\":\"target:t_p_parameters\",\"to\":\"target:transactionCurrency:\",\"fromPort\":\"target:t_p_parameters\",\"toPort\":\"target:transactionCurrency:\",\"visible\":true,\"common\":false},{\"from\":\"target:t_p_parameters\",\"to\":\"target:transactionId:\",\"fromPort\":\"target:t_p_parameters\",\"toPort\":\"target:transactionId:\",\"visible\":true,\"common\":false},{\"from\":\"target:t_p_parameters\",\"to\":\"target:TransactionType_id:\",\"fromPort\":\"target:t_p_parameters\",\"toPort\":\"target:TransactionType_id:\",\"visible\":true,\"common\":false}],\"blockCount\":{\"variableCount\":0},\"variableMap\":{},\"xmlMappingOverride\":true}",
    "oVisualMappingData" : "{\"nodeDataArray\":[{\"isGroup\":true,\"key\":\"response_out\",\"text\":\"ACHTransactions\",\"xy\":\"770 100\"},{\"isGroup\":true,\"key\":\"response_in\",\"text\":\"dbpACHServices (1.0).createTransaction\",\"xy\":\"150 100\"}],\"linkDataArray\":[{\"from\":\"target\",\"to\":\"target:ACHTransactions\",\"fromPort\":\"target\",\"toPort\":\"target:ACHTransactions\",\"visible\":true,\"common\":false},{\"from\":\"target:ACHTransactions\",\"to\":\"target:ACHTransactions:t_p_fields\",\"fromPort\":\"target:ACHTransactions\",\"toPort\":\"target:ACHTransactions:t_p_fields\",\"visible\":true,\"common\":false},{\"from\":\"target:ACHTransactions:t_p_fields\",\"to\":\"target:ACHTransactions:BBGeneralTransactionType_id:\",\"fromPort\":\"target:ACHTransactions:t_p_fields\",\"toPort\":\"target:ACHTransactions:BBGeneralTransactionType_id:\",\"visible\":true,\"common\":false},{\"from\":\"target:ACHTransactions:t_p_fields\",\"to\":\"target:ACHTransactions:Status:\",\"fromPort\":\"target:ACHTransactions:t_p_fields\",\"toPort\":\"target:ACHTransactions:Status:\",\"visible\":true,\"common\":false},{\"from\":\"target:ACHTransactions:t_p_fields\",\"to\":\"target:ACHTransactions:TemplateRequestType_id:\",\"fromPort\":\"target:ACHTransactions:t_p_fields\",\"toPort\":\"target:ACHTransactions:TemplateRequestType_id:\",\"visible\":true,\"common\":false},{\"from\":\"target:ACHTransactions:t_p_fields\",\"to\":\"target:ACHTransactions:Request_id:\",\"fromPort\":\"target:ACHTransactions:t_p_fields\",\"toPort\":\"target:ACHTransactions:Request_id:\",\"visible\":true,\"common\":false},{\"from\":\"target:ACHTransactions:t_p_fields\",\"to\":\"target:ACHTransactions:userName:\",\"fromPort\":\"target:ACHTransactions:t_p_fields\",\"toPort\":\"target:ACHTransactions:userName:\",\"visible\":true,\"common\":false},{\"from\":\"target:ACHTransactions:t_p_fields\",\"to\":\"target:ACHTransactions:DebitAccount:\",\"fromPort\":\"target:ACHTransactions:t_p_fields\",\"toPort\":\"target:ACHTransactions:DebitAccount:\",\"visible\":true,\"common\":false},{\"from\":\"target:ACHTransactions:t_p_fields\",\"to\":\"target:ACHTransactions:CreatedOn:\",\"fromPort\":\"target:ACHTransactions:t_p_fields\",\"toPort\":\"target:ACHTransactions:CreatedOn:\",\"visible\":true,\"common\":false},{\"from\":\"target:ACHTransactions:t_p_fields\",\"to\":\"target:ACHTransactions:MaxAmount:\",\"fromPort\":\"target:ACHTransactions:t_p_fields\",\"toPort\":\"target:ACHTransactions:MaxAmount:\",\"visible\":true,\"common\":false},{\"from\":\"target:ACHTransactions:t_p_fields\",\"to\":\"target:ACHTransactions:TemplateType_id:\",\"fromPort\":\"target:ACHTransactions:t_p_fields\",\"toPort\":\"target:ACHTransactions:TemplateType_id:\",\"visible\":true,\"common\":false},{\"from\":\"target:ACHTransactions:t_p_fields\",\"to\":\"target:ACHTransactions:CompanyName:\",\"fromPort\":\"target:ACHTransactions:t_p_fields\",\"toPort\":\"target:ACHTransactions:CompanyName:\",\"visible\":true,\"common\":false},{\"from\":\"target:ACHTransactions:t_p_fields\",\"to\":\"target:ACHTransactions:RequestType:\",\"fromPort\":\"target:ACHTransactions:t_p_fields\",\"toPort\":\"target:ACHTransactions:RequestType:\",\"visible\":true,\"common\":false},{\"from\":\"target:ACHTransactions:t_p_fields\",\"to\":\"target:ACHTransactions:TemplateTypeValue:\",\"fromPort\":\"target:ACHTransactions:t_p_fields\",\"toPort\":\"target:ACHTransactions:TemplateTypeValue:\",\"visible\":true,\"common\":false},{\"from\":\"target:ACHTransactions:t_p_fields\",\"to\":\"target:ACHTransactions:softDelete:\",\"fromPort\":\"target:ACHTransactions:t_p_fields\",\"toPort\":\"target:ACHTransactions:softDelete:\",\"visible\":true,\"common\":false},{\"from\":\"target:ACHTransactions:t_p_fields\",\"to\":\"target:ACHTransactions:TransactionType_id:\",\"fromPort\":\"target:ACHTransactions:t_p_fields\",\"toPort\":\"target:ACHTransactions:TransactionType_id:\",\"visible\":true,\"common\":false},{\"from\":\"target:ACHTransactions:t_p_fields\",\"to\":\"target:ACHTransactions:CreatedBy:\",\"fromPort\":\"target:ACHTransactions:t_p_fields\",\"toPort\":\"target:ACHTransactions:CreatedBy:\",\"visible\":true,\"common\":false},{\"from\":\"target:ACHTransactions:t_p_fields\",\"to\":\"target:ACHTransactions:Company_id:\",\"fromPort\":\"target:ACHTransactions:t_p_fields\",\"toPort\":\"target:ACHTransactions:Company_id:\",\"visible\":true,\"common\":false},{\"from\":\"target:ACHTransactions:t_p_fields\",\"to\":\"target:ACHTransactions:TransactionTypeValue:\",\"fromPort\":\"target:ACHTransactions:t_p_fields\",\"toPort\":\"target:ACHTransactions:TransactionTypeValue:\",\"visible\":true,\"common\":false},{\"from\":\"target:ACHTransactions:t_p_fields\",\"to\":\"target:ACHTransactions:StatusValue:\",\"fromPort\":\"target:ACHTransactions:t_p_fields\",\"toPort\":\"target:ACHTransactions:StatusValue:\",\"visible\":true,\"common\":false},{\"from\":\"target:ACHTransactions:t_p_fields\",\"to\":\"target:ACHTransactions:Transaction_id:\",\"fromPort\":\"target:ACHTransactions:t_p_fields\",\"toPort\":\"target:ACHTransactions:Transaction_id:\",\"visible\":true,\"common\":false},{\"from\":\"target:ACHTransactions:t_p_fields\",\"to\":\"target:ACHTransactions:EffectiveDate:\",\"fromPort\":\"target:ACHTransactions:t_p_fields\",\"toPort\":\"target:ACHTransactions:EffectiveDate:\",\"visible\":true,\"common\":false},{\"from\":\"target:ACHTransactions:t_p_fields\",\"to\":\"target:ACHTransactions:TemplateName:\",\"fromPort\":\"target:ACHTransactions:t_p_fields\",\"toPort\":\"target:ACHTransactions:TemplateName:\",\"visible\":true,\"common\":false},{\"from\":\"target:ACHTransactions:t_p_fields\",\"to\":\"target:ACHTransactions:ConfirmationNumber:\",\"fromPort\":\"target:ACHTransactions:t_p_fields\",\"toPort\":\"target:ACHTransactions:ConfirmationNumber:\",\"visible\":true,\"common\":false},{\"from\":\"target:ACHTransactions:t_p_fields\",\"to\":\"target:ACHTransactions:Approver:\",\"fromPort\":\"target:ACHTransactions:t_p_fields\",\"toPort\":\"target:ACHTransactions:Approver:\",\"visible\":true,\"common\":false},{\"from\":\"target:ACHTransactions:t_p_fields\",\"to\":\"target:ACHTransactions:Records:\",\"fromPort\":\"target:ACHTransactions:t_p_fields\",\"toPort\":\"target:ACHTransactions:Records:\",\"visible\":true,\"common\":false},{\"from\":\"target:ACHTransactions:t_p_fields\",\"to\":\"target:ACHTransactions:TemplateDescription:\",\"fromPort\":\"target:ACHTransactions:t_p_fields\",\"toPort\":\"target:ACHTransactions:TemplateDescription:\",\"visible\":true,\"common\":false},{\"from\":\"target:ACHTransactions:t_p_fields\",\"to\":\"target:ACHTransactions:TotalAmount:\",\"fromPort\":\"target:ACHTransactions:t_p_fields\",\"toPort\":\"target:ACHTransactions:TotalAmount:\",\"visible\":true,\"common\":false},{\"from\":\"target:ACHTransactions:t_p_fields\",\"to\":\"target:ACHTransactions:ReferenceID:\",\"fromPort\":\"target:ACHTransactions:t_p_fields\",\"toPort\":\"target:ACHTransactions:ReferenceID:\",\"visible\":true,\"common\":false},{\"from\":\"target:ACHTransactions:t_p_fields\",\"to\":\"target:ACHTransactions:opstatus:\",\"fromPort\":\"target:ACHTransactions:t_p_fields\",\"toPort\":\"target:ACHTransactions:opstatus:\",\"visible\":true,\"common\":false},{\"from\":\"target:ACHTransactions:t_p_fields\",\"to\":\"target:ACHTransactions:httpStatusCode:\",\"fromPort\":\"target:ACHTransactions:t_p_fields\",\"toPort\":\"target:ACHTransactions:httpStatusCode:\",\"visible\":true,\"common\":false},{\"from\":\"target:ACHTransactions:t_p_fields\",\"to\":\"target:ACHTransactions:dbpErrCode:\",\"fromPort\":\"target:ACHTransactions:t_p_fields\",\"toPort\":\"target:ACHTransactions:dbpErrCode:\",\"visible\":true,\"common\":false},{\"from\":\"target:ACHTransactions:t_p_fields\",\"to\":\"target:ACHTransactions:dbpErrMsg:\",\"fromPort\":\"target:ACHTransactions:t_p_fields\",\"toPort\":\"target:ACHTransactions:dbpErrMsg:\",\"visible\":true,\"common\":false},{\"from\":\"target:ACHTransactions:t_p_fields\",\"to\":\"target:ACHTransactions:featureActionId:\",\"fromPort\":\"target:ACHTransactions:t_p_fields\",\"toPort\":\"target:ACHTransactions:featureActionId:\",\"visible\":true,\"common\":false},{\"from\":\"target:ACHTransactions:t_p_fields\",\"to\":\"target:ACHTransactions:queryType:\",\"fromPort\":\"target:ACHTransactions:t_p_fields\",\"toPort\":\"target:ACHTransactions:queryType:\",\"visible\":true,\"common\":false},{\"from\":\"target:ACHTransactions:t_p_fields\",\"to\":\"target:ACHTransactions:searchString:\",\"fromPort\":\"target:ACHTransactions:t_p_fields\",\"toPort\":\"target:ACHTransactions:searchString:\",\"visible\":true,\"common\":false},{\"from\":\"target:ACHTransactions:t_p_fields\",\"to\":\"target:ACHTransactions:sortByParam:\",\"fromPort\":\"target:ACHTransactions:t_p_fields\",\"toPort\":\"target:ACHTransactions:sortByParam:\",\"visible\":true,\"common\":false},{\"from\":\"target:ACHTransactions:t_p_fields\",\"to\":\"target:ACHTransactions:sortOrder:\",\"fromPort\":\"target:ACHTransactions:t_p_fields\",\"toPort\":\"target:ACHTransactions:sortOrder:\",\"visible\":true,\"common\":false},{\"from\":\"target:ACHTransactions:t_p_fields\",\"to\":\"target:ACHTransactions:pageSize:\",\"fromPort\":\"target:ACHTransactions:t_p_fields\",\"toPort\":\"target:ACHTransactions:pageSize:\",\"visible\":true,\"common\":false},{\"from\":\"target:ACHTransactions:t_p_fields\",\"to\":\"target:ACHTransactions:pageOffset:\",\"fromPort\":\"target:ACHTransactions:t_p_fields\",\"toPort\":\"target:ACHTransactions:pageOffset:\",\"visible\":true,\"common\":false},{\"from\":\"target:ACHTransactions:t_p_fields\",\"to\":\"target:ACHTransactions:receivedApprovals:\",\"fromPort\":\"target:ACHTransactions:t_p_fields\",\"toPort\":\"target:ACHTransactions:receivedApprovals:\",\"visible\":true,\"common\":false},{\"from\":\"target:ACHTransactions:t_p_fields\",\"to\":\"target:ACHTransactions:requiredApprovals:\",\"fromPort\":\"target:ACHTransactions:t_p_fields\",\"toPort\":\"target:ACHTransactions:requiredApprovals:\",\"visible\":true,\"common\":false},{\"from\":\"target:ACHTransactions:t_p_fields\",\"to\":\"target:ACHTransactions:AccountName:\",\"fromPort\":\"target:ACHTransactions:t_p_fields\",\"toPort\":\"target:ACHTransactions:AccountName:\",\"visible\":true,\"common\":false},{\"from\":\"target:ACHTransactions:t_p_fields\",\"to\":\"target:ACHTransactions:filterByParam:\",\"fromPort\":\"target:ACHTransactions:t_p_fields\",\"toPort\":\"target:ACHTransactions:filterByParam:\",\"visible\":true,\"common\":false},{\"from\":\"target:ACHTransactions:t_p_fields\",\"to\":\"target:ACHTransactions:filterByValue:\",\"fromPort\":\"target:ACHTransactions:t_p_fields\",\"toPort\":\"target:ACHTransactions:filterByValue:\",\"visible\":true,\"common\":false},{\"from\":\"target:ACHTransactions:t_p_fields\",\"to\":\"target:ACHTransactions:amICreator:\",\"fromPort\":\"target:ACHTransactions:t_p_fields\",\"toPort\":\"target:ACHTransactions:amICreator:\",\"visible\":true,\"common\":false},{\"from\":\"target:ACHTransactions:t_p_fields\",\"to\":\"target:ACHTransactions:amIApprover:\",\"fromPort\":\"target:ACHTransactions:t_p_fields\",\"toPort\":\"target:ACHTransactions:amIApprover:\",\"visible\":true,\"common\":false},{\"from\":\"target:ACHTransactions:t_p_fields\",\"to\":\"target:ACHTransactions:TemplateRequestTypeValue:\",\"fromPort\":\"target:ACHTransactions:t_p_fields\",\"toPort\":\"target:ACHTransactions:TemplateRequestTypeValue:\",\"visible\":true,\"common\":false},{\"from\":\"target:ACHTransactions:t_p_fields\",\"to\":\"target:ACHTransactions:transactionId:\",\"fromPort\":\"target:ACHTransactions:t_p_fields\",\"toPort\":\"target:ACHTransactions:transactionId:\",\"visible\":true,\"common\":false}],\"blockCount\":{\"variableCount\":0},\"variableMap\":{},\"xmlMappingOverride\":true}",
    "applyCommonMapping" : false,
    "applyRequestCommonMapping" : false,
    "applyResponseCommonMapping" : false,
    "backendMeta" : {
      "serviceName" : "dbpACHServices",
      "serviceVersion" : "1.0",
      "operationName" : "createTransaction"
    },
    "relationshipHierarchyMapping" : {
      "children" : [ ],
      "name" : "ACHTransactions",
      "actions" : { },
      "selected" : true
    },
    "requestXmlMappingOverride" : true,
    "responseXmlMappingOverride" : true
  }
}