{
  "operationConfig" : {
    "name" : "updateBinarymedia8939",
    "type" : "MappedToBackend",
    "cachable" : false,
    "smsEnabled" : false,
    "security" : "authorized_app_user",
    "responseEncoding" : "UTF-8",
    "httpMethod" : "GET",
    "decodeResponseBody" : false,
    "referencingEndpoint" : "default",
    "inputs" : [ {
      "id" : "id",
      "scope" : "request",
      "dataType" : "string",
      "encode" : true,
      "passNull" : false
    } ],
    "applyCommonMapping" : true,
    "applyRequestCommonMapping" : true,
    "applyResponseCommonMapping" : true,
    "entityMetadata" : "{\"entityAttributeTypeList\":[{\"name\":\"id\",\"jdbcType\":12,\"columnTypeName\":\"VARCHAR\",\"columnDecimalDigits\":0,\"autoGenerated\":false,\"creatable\":true,\"updatable\":false,\"primary\":true,\"softDelete\":false,\"lastModified\":false},{\"name\":\"Name\",\"jdbcType\":12,\"columnTypeName\":\"VARCHAR\",\"columnDecimalDigits\":0,\"autoGenerated\":false,\"creatable\":true,\"updatable\":true,\"primary\":false,\"softDelete\":false,\"lastModified\":false},{\"name\":\"Type\",\"jdbcType\":12,\"columnTypeName\":\"VARCHAR\",\"columnDecimalDigits\":0,\"autoGenerated\":false,\"creatable\":true,\"updatable\":true,\"primary\":false,\"softDelete\":false,\"lastModified\":false},{\"name\":\"Description\",\"jdbcType\":12,\"columnTypeName\":\"VARCHAR\",\"columnDecimalDigits\":0,\"autoGenerated\":false,\"creatable\":true,\"updatable\":true,\"primary\":false,\"softDelete\":false,\"lastModified\":false},{\"name\":\"Url\",\"jdbcType\":12,\"columnTypeName\":\"VARCHAR\",\"columnDecimalDigits\":0,\"autoGenerated\":false,\"creatable\":true,\"updatable\":true,\"primary\":false,\"softDelete\":false,\"lastModified\":false},{\"name\":\"Content\",\"jdbcType\":-4,\"columnTypeName\":\"MEDIUMBLOB\",\"columnDecimalDigits\":0,\"autoGenerated\":false,\"creatable\":true,\"updatable\":true,\"primary\":false,\"softDelete\":false,\"lastModified\":false},{\"name\":\"Size\",\"jdbcType\":12,\"columnTypeName\":\"VARCHAR\",\"columnDecimalDigits\":0,\"autoGenerated\":false,\"creatable\":true,\"updatable\":true,\"primary\":false,\"softDelete\":false,\"lastModified\":false},{\"name\":\"createdby\",\"jdbcType\":12,\"columnTypeName\":\"VARCHAR\",\"columnDecimalDigits\":0,\"autoGenerated\":false,\"creatable\":true,\"updatable\":true,\"primary\":false,\"softDelete\":false,\"lastModified\":false},{\"name\":\"modifiedby\",\"jdbcType\":12,\"columnTypeName\":\"VARCHAR\",\"columnDecimalDigits\":0,\"autoGenerated\":false,\"creatable\":true,\"updatable\":true,\"primary\":false,\"softDelete\":false,\"lastModified\":false},{\"name\":\"createdts\",\"jdbcType\":93,\"columnTypeName\":\"TIMESTAMP\",\"columnDecimalDigits\":0,\"autoGenerated\":false,\"creatable\":true,\"updatable\":true,\"primary\":false,\"softDelete\":false,\"lastModified\":false},{\"name\":\"lastmodifiedts\",\"jdbcType\":93,\"columnTypeName\":\"TIMESTAMP\",\"columnDecimalDigits\":0,\"autoGenerated\":false,\"creatable\":true,\"updatable\":true,\"primary\":false,\"softDelete\":false,\"lastModified\":false},{\"name\":\"synctimestamp\",\"jdbcType\":93,\"columnTypeName\":\"TIMESTAMP\",\"columnDecimalDigits\":0,\"autoGenerated\":false,\"creatable\":true,\"updatable\":true,\"primary\":false,\"softDelete\":false,\"lastModified\":false},{\"name\":\"softdeleteflag\",\"jdbcType\":-7,\"columnTypeName\":\"BIT\",\"columnDecimalDigits\":0,\"autoGenerated\":false,\"creatable\":true,\"updatable\":true,\"primary\":false,\"softDelete\":true,\"lastModified\":false}],\"relationshipTypeList\":[{\"targetEntityType\":{\"name\":\"messageattachment\",\"schemaName\":\"dbxdb\"},\"relationshipAttributeTypeList\":[{\"sourceEntityAttributeType\":{\"name\":\"id\",\"jdbcType\":0,\"columnDecimalDigits\":0,\"autoGenerated\":false,\"creatable\":false,\"updatable\":false,\"primary\":false,\"softDelete\":false,\"lastModified\":false},\"targetEntityAttributeType\":{\"name\":\"Media_id\",\"jdbcType\":0,\"columnDecimalDigits\":0,\"autoGenerated\":false,\"creatable\":false,\"updatable\":false,\"primary\":false,\"softDelete\":false,\"lastModified\":false}}],\"cascadeDelete\":false,\"relationshipType\":\"ONE_TO_MANY\"}],\"name\":\"media\",\"schemaName\":\"dbxdb\",\"entityType\":\"com.kony.rdbms.metadata.model.AnnotatedTable\"}",
    "opcode" : "updateBinary",
    "backendMeta" : {
      "qualifiedObjectName" : "dbxdb.media",
      "backendObjectName" : "media"
    },
    "relationshipHierarchyMapping" : {
      "children" : [ ],
      "name" : "media",
      "actions" : { },
      "selected" : true
    },
    "requestXmlMappingOverride" : false,
    "responseXmlMappingOverride" : false
  }
}