{
    "DNDConfig": null,
    "_bottom_": {
        "type": "string",
        "value": "0dp"
    },
    "_left_": {
        "type": "string",
        "value": "20dp"
    },
    "_margin_": [
        0,
        0,
        0,
        0
    ],
    "_orientation_": 6,
    "_padding_": [
        0,
        0,
        0,
        0
    ],
    "_percent_": true,
    "_right_": {
        "type": "string",
        "value": "20dp"
    },
    "_skin_": "s966eaf1ea1441148b4828270a782f8b",
    "_top_": {
        "type": "string",
        "value": "95dp"
    },
    "allboxes": [],
    "autogrowmode": 0,
    "canUpdateUI": true,
    "children": [
        "flxToAccountHints",
        "flxNoTransactions",
        "btnAddRecipient"
    ],
    "clipbounds": true,
    "containerweight": 100,
    "enablescrolling": true,
    "id": "flxSuggestions",
    "info": null,
    "iscustomlayout": false,
    "isvisible": true,
    "kuid": "h800d1ac539140e0910562c72011a661",
    "layouttype": 4,
    "name": "kony.ui.FlexContainer",
    "parent": "flxMainContainer",
    "pf": "frmtransfersAccountNumberEurope",
    "retaincontentalignment": false,
    "retainflexpositionproperties": false,
    "retainflowhorizontalalignment": false,
    "snapgridsize": 10,
    "snaptogrid": true,
    "wType": "FlexContainer",
    "widgetalignment": 1,
    "zindex": 2
}