<?xml version="1.0" encoding="UTF-8" standalone="yes"?>
<service serviceGroup="" cachable="false" cacheduration="" description="" endpoint="default" groupType="" id="getCDPConsentGateway" passwordencrypted="false" security="authorized_app_user" type="javaConnector" smscode="" smsenabled="false">
    <service-config>
        <config-param api-version="" appid="" name="preprocessorname" value=""/>
        <config-param api-version="" appid="" name="postprocessorname" value=""/>
        <config-param api-version="" appid="" name="preprocessorJS" value=""/>
        <config-param api-version="" appid="" name="postprocessorJS" value=""/>
        <config-param api-version="" appid="" name="preprocessorRules" value=""/>
        <config-param api-version="" appid="" name="postprocessorRules" value=""/>
        <config-param api-version="" appid="" name="kony_http_supported_methods" value="POST"/>
        <config-param api-version="" appid="" name="className" value="com.temenos.dbx.consents.javaservice.GetCDPConsents"/>
        <config-param api-version="" appid="" name="methodName" value="getCDPConsentGateway"/>
        <config-param api-version="" appid="" name="sockettimeout" value=""/>
        <config-param api-version="" appid="" name="totalRateLimit" value="10000"/>
    </service-config>
    <service-input passthrough="false"/>
    <service-output passthrough="false">
        <dataset defaultvalue="" id="consentTypes" order="" paramOrder="1" parentOrder="0" src="" testvalue="">
            <dataset defaultvalue="" id="consents" order="" paramOrder="3" parentOrder="1" src="" testvalue="">
                <dataset defaultvalue="" id="subTypes" order="" paramOrder="9" parentOrder="3" src="" testvalue="">
                    <param datatype="string" defaultvalue="" description="" encode="true" format="None" formatvalue="" name="consentSubType" order="" paramOrder="10" parentOrder="9" passnull="false" sms-name="" src="" sourcevalue="" srcformatvalue="" target="response" targetdatatype="java.lang.String" testvalue="" value="">
                        <accessType></accessType>
                    </param>
                    <param datatype="string" defaultvalue="" description="" encode="true" format="None" formatvalue="" name="consentSubTypeGiven" order="" paramOrder="11" parentOrder="9" passnull="false" sms-name="" src="" sourcevalue="" srcformatvalue="" target="response" targetdatatype="java.lang.String" testvalue="" value="">
                        <accessType></accessType>
                    </param>
                </dataset>
                <param datatype="string" defaultvalue="" description="" encode="true" format="None" formatvalue="" name="consentType" order="" paramOrder="4" parentOrder="3" passnull="false" sms-name="" src="" sourcevalue="" srcformatvalue="" target="response" targetdatatype="java.lang.String" testvalue="" value="">
                    <accessType></accessType>
                </param>
                <param datatype="string" defaultvalue="" description="" encode="true" format="None" formatvalue="" name="consentGiven" order="" paramOrder="5" parentOrder="3" passnull="false" sms-name="" src="" sourcevalue="" srcformatvalue="" target="response" targetdatatype="java.lang.String" testvalue="" value="">
                    <accessType></accessType>
                </param>
                <param datatype="string" defaultvalue="" description="" encode="true" format="None" formatvalue="" name="consentTypeName" order="" paramOrder="6" parentOrder="3" passnull="false" sms-name="" src="" sourcevalue="" srcformatvalue="" target="response" targetdatatype="java.lang.String" testvalue="" value="">
                    <accessType></accessType>
                </param>
                <param datatype="string" defaultvalue="" description="" encode="true" format="None" formatvalue="" name="consentBlock" order="" paramOrder="7" parentOrder="3" passnull="false" sms-name="" src="" sourcevalue="" srcformatvalue="" target="response" targetdatatype="java.lang.String" testvalue="" value="">
                    <accessType></accessType>
                </param>
                <param datatype="string" defaultvalue="" description="" encode="true" format="None" formatvalue="" name="blockNotes" order="" paramOrder="8" parentOrder="3" passnull="false" sms-name="" src="" sourcevalue="" srcformatvalue="" target="response" targetdatatype="java.lang.String" testvalue="" value="">
                    <accessType></accessType>
                </param>
            </dataset>
            <param datatype="string" defaultvalue="" description="" encode="true" format="None" formatvalue="" name="arrangementId" order="" paramOrder="2" parentOrder="1" passnull="false" sms-name="" src="" sourcevalue="" srcformatvalue="" target="response" targetdatatype="java.lang.String" testvalue="" value="">
                <accessType></accessType>
            </param>
            <param datatype="string" defaultvalue="" description="" encode="true" format="None" formatvalue="" name="status" order="" paramOrder="13" parentOrder="1" passnull="false" sms-name="" src="" sourcevalue="" srcformatvalue="" target="response" targetdatatype="java.lang.String" testvalue="" value="">
                <accessType></accessType>
            </param>
        </dataset>
        <param datatype="string" defaultvalue="" description="" encode="true" format="None" formatvalue="" name="errmsg" order="" paramOrder="12" parentOrder="0" passnull="false" sms-name="" src="" sourcevalue="" srcformatvalue="" target="response" targetdatatype="java.lang.String" testvalue="" value="">
            <accessType></accessType>
        </param>
    </service-output>
</service>
