{
  "operationConfig" : {
    "name" : "VerifyCaptcha1364",
    "type" : "MappedToBackend",
    "cachable" : false,
    "smsEnabled" : false,
    "security" : "public",
    "responseEncoding" : "UTF-8",
    "httpMethod" : "GET",
    "decodeResponseBody" : false,
    "iMapping" : "<?xml version=\"1.0\" encoding=\"UTF-8\" standalone=\"yes\"?><mapper xmlns=\"http://www.kony.com/ns/mapper\"><map inputpath=\"request_in\" outputpath=\"request_out\"><set-param inputpath=\"serviceKey\" outputpath=\"serviceKey\"/></map></mapper>",
    "oMapping" : "<?xml version=\"1.0\" encoding=\"UTF-8\" standalone=\"yes\"?><mapper xmlns=\"http://www.kony.com/ns/mapper\"><map inputpath=\"response_in\" outputpath=\"response_out\"><set-param inputpath=\"encodedImage\" outputpath=\"encodedImage\"/></map></mapper>",
    "applyCommonMapping" : true,
    "applyRequestCommonMapping" : true,
    "applyResponseCommonMapping" : true,
    "backendMeta" : {
      "serviceName" : "dbpProductServices",
      "serviceVersion" : "1.0",
      "operationName" : "VerifyCaptcha"
    },
    "relationshipHierarchyMapping" : {
      "children" : [ ],
      "name" : "Security",
      "actions" : { },
      "selected" : true
    },
    "requestXmlMappingOverride" : false,
    "responseXmlMappingOverride" : false
  }
}