{
    "AS_Button_j66da00585a548c28186a8e9a94caff9": {
        "id": "AS_Button_j66da00585a548c28186a8e9a94caff9",
        "type": "ACTION_SEQUENCE",
        "params": [{
            "datatype": "collection",
            "name": "eventobject"
        }],
        "contextObj": {
            "name": "frmTransfersPhoneNumberEurope",
            "type": "forms",
            "platform": "",
            "KUID": "c5fa7b64e66f42e68ce34cef04be0c36"
        },
        "language": "js",
        "actions": [{
            "id": "ADD_SNIPPET_aa584fcf69f94e6a9e69c8b29690cb3a",
            "type": "ADD_SNIPPET",
            "codeSnippet": "this.setKeypadChar(1);",
            "parentId": null
        }]
    }
}