{
    "AS_BarButtonItem_c007407d14794f8d853ef4e02714efbd": {
        "id": "AS_BarButtonItem_c007407d14794f8d853ef4e02714efbd",
        "type": "ACTION_SEQUENCE",
        "params": [{
            "datatype": "collection",
            "name": "eventobject"
        }],
        "language": "js",
        "actions": [{
            "id": "ADD_SNIPPET_d3957409fde74a618772ce7a979f10b2",
            "type": "ADD_SNIPPET",
            "codeSnippet": "this.onClickCancel();",
            "parentId": null
        }]
    }
}