{
    "AS_Button_ac954bf2e2704c82aa49c4c0a0ee2bce": {
        "id": "AS_Button_ac954bf2e2704c82aa49c4c0a0ee2bce",
        "type": "ACTION_SEQUENCE",
        "params": [{
            "datatype": "collection",
            "name": "eventobject"
        }],
        "contextObj": {
            "name": "frmCreateGoalMonths",
            "type": "forms",
            "platform": null,
            "KUID": "e3e9161896e14650a7267e5612929539"
        },
        "language": "js",
        "actions": [{
            "id": "ADD_SNIPPET_ide_onClick_c016f925c2244d8caaaee10d7f9d6635",
            "type": "ADD_SNIPPET",
            "codeSnippet": "this.setKeypadChar(7);",
            "callbackType": null
        }]
    }
}