{
    "AS_BarButtonItem_b3377372322f42eeb39855386e2bddb0": {
        "id": "AS_BarButtonItem_b3377372322f42eeb39855386e2bddb0",
        "type": "ACTION_SEQUENCE",
        "params": [{
            "datatype": "collection",
            "name": "eventobject"
        }],
        "language": "js",
        "actions": [{
            "id": "ADD_SNIPPET_fa34920119054bf0927de7cf50d154c0",
            "type": "ADD_SNIPPET",
            "codeSnippet": "this.backNavigation();",
            "parentId": null
        }]
    }
}