{
    "AS_Form_e9d55384e1a849db89cbcd738710ff0b": {
        "id": "AS_Form_e9d55384e1a849db89cbcd738710ff0b",
        "type": "ACTION_SEQUENCE",
        "params": [{
            "datatype": "collection",
            "name": "eventobject"
        }],
        "contextObj": {
            "name": "frmGoalsAcknowledgement",
            "type": "forms",
            "platform": null,
            "KUID": "db72da62a43841ac9eefe5eda49760dd"
        },
        "language": "js",
        "actions": [{
            "id": "ADD_SNIPPET_ide_preShow_g4c565d159e240f0a42f23ce69f0fe1d",
            "type": "ADD_SNIPPET",
            "codeSnippet": "this.preShow();",
            "callbackType": null
        }]
    }
}