<?xml version="1.0" encoding="UTF-8" standalone="yes"?>
<service serviceGroup="" cachable="false" cacheduration="" description="" endpoint="default" groupType="" id="EditOwnAccountTransaction" passwordencrypted="false" security="public" type="javaConnector" smscode="" smsenabled="false">
    <service-config>
        <config-param api-version="" appid="" name="preprocessorname" value=""/>
        <config-param api-version="" appid="" name="postprocessorname" value=""/>
        <config-param api-version="" appid="" name="preprocessorJS" value=""/>
        <config-param api-version="" appid="" name="postprocessorJS" value=""/>
        <config-param api-version="" appid="" name="preprocessorRules" value=""/>
        <config-param api-version="" appid="" name="postprocessorRules" value=""/>
        <config-param api-version="" appid="" name="kony_http_supported_methods" value="POST"/>
        <config-param api-version="" appid="" name="className" value="com.temenos.dbx.product.transactionservices.javaservices.EditOwnAccountTransferOperation"/>
        <config-param api-version="" appid="" name="methodName" value="EditOwnAccountTransaction"/>
        <config-param api-version="" appid="" name="sockettimeout" value=""/>
    </service-config>
    <service-input passthrough="false">
        <param datatype="string" defaultvalue="" description="" encode="true" format="None" formatvalue="" name="amount" order="" paramOrder="1" parentOrder="-1" passnull="false" sms-name="" src="request" sourcevalue="" srcformatvalue="" target="request" targetdatatype="java.lang.String" testvalue="" value="">
            <accessType></accessType>
        </param>
        <param datatype="string" defaultvalue="" description="" encode="true" format="None" formatvalue="" name="frequencyEndDate" order="" paramOrder="2" parentOrder="-1" passnull="false" sms-name="" src="request" sourcevalue="" srcformatvalue="" target="request" targetdatatype="java.lang.String" testvalue="" value="">
            <accessType></accessType>
        </param>
        <param datatype="string" defaultvalue="" description="" encode="true" format="None" formatvalue="" name="frequencyType" order="" paramOrder="3" parentOrder="-1" passnull="false" sms-name="" src="request" sourcevalue="" srcformatvalue="" target="request" targetdatatype="java.lang.String" testvalue="" value="">
            <accessType></accessType>
        </param>
        <param datatype="string" defaultvalue="" description="" encode="true" format="None" formatvalue="" name="fromAccountNumber" order="" paramOrder="4" parentOrder="-1" passnull="false" sms-name="" src="request" sourcevalue="" srcformatvalue="" target="request" targetdatatype="java.lang.String" testvalue="" value="">
            <accessType></accessType>
        </param>
        <param datatype="string" defaultvalue="" description="" encode="true" format="None" formatvalue="" name="isScheduled" order="" paramOrder="5" parentOrder="-1" passnull="false" sms-name="" src="request" sourcevalue="" srcformatvalue="" target="request" targetdatatype="java.lang.String" testvalue="" value="">
            <accessType></accessType>
        </param>
        <param datatype="string" defaultvalue="" description="" encode="true" format="None" formatvalue="" name="scheduledDate" order="" paramOrder="6" parentOrder="-1" passnull="false" sms-name="" src="request" sourcevalue="" srcformatvalue="" target="request" targetdatatype="java.lang.String" testvalue="" value="">
            <accessType></accessType>
        </param>
        <param datatype="string" defaultvalue="" description="" encode="true" format="None" formatvalue="" name="toAccountNumber" order="" paramOrder="7" parentOrder="-1" passnull="false" sms-name="" src="request" sourcevalue="" srcformatvalue="" target="request" targetdatatype="java.lang.String" testvalue="" value="">
            <accessType></accessType>
        </param>
        <param datatype="string" defaultvalue="" description="" encode="true" format="None" formatvalue="" name="transactionsNotes" order="" paramOrder="8" parentOrder="-1" passnull="false" sms-name="" src="request" sourcevalue="" srcformatvalue="" target="request" targetdatatype="java.lang.String" testvalue="" value="">
            <accessType></accessType>
        </param>
        <param datatype="string" defaultvalue="" description="" encode="true" format="None" formatvalue="" name="transactionType" order="" paramOrder="9" parentOrder="-1" passnull="false" sms-name="" src="request" sourcevalue="" srcformatvalue="" target="request" targetdatatype="java.lang.String" testvalue="" value="">
            <accessType></accessType>
        </param>
        <param datatype="string" defaultvalue="" description="" encode="true" format="None" formatvalue="" name="transactionCurrency" order="" paramOrder="10" parentOrder="-1" passnull="false" sms-name="" src="request" sourcevalue="" srcformatvalue="" target="request" targetdatatype="java.lang.String" testvalue="" value="">
            <accessType></accessType>
        </param>
        <param datatype="string" defaultvalue="" description="" encode="true" format="None" formatvalue="" name="fromAccountCurrency" order="" paramOrder="11" parentOrder="-1" passnull="false" sms-name="" src="request" sourcevalue="" srcformatvalue="" target="request" targetdatatype="java.lang.String" testvalue="" value="">
            <accessType></accessType>
        </param>
        <param datatype="string" defaultvalue="" description="" encode="true" format="None" formatvalue="" name="numberOfRecurrences" order="" paramOrder="12" parentOrder="-1" passnull="false" sms-name="" src="request" sourcevalue="" srcformatvalue="" target="request" targetdatatype="java.lang.String" testvalue="" value="">
            <accessType></accessType>
        </param>
        <param datatype="string" defaultvalue="" description="" encode="true" format="None" formatvalue="" name="toAccountCurrency" order="" paramOrder="13" parentOrder="-1" passnull="false" sms-name="" src="request" sourcevalue="" srcformatvalue="" target="request" targetdatatype="java.lang.String" testvalue="" value="">
            <accessType></accessType>
        </param>
        <param datatype="string" defaultvalue="" description="" encode="true" format="None" formatvalue="" name="transactionId" order="" paramOrder="14" parentOrder="-1" passnull="false" sms-name="" src="request" sourcevalue="" srcformatvalue="" target="request" targetdatatype="java.lang.String" testvalue="" value="">
            <accessType></accessType>
        </param>
        <param datatype="string" defaultvalue="" description="" encode="true" format="None" formatvalue="" name="confirmationNumber" order="" paramOrder="15" parentOrder="-1" passnull="false" sms-name="" src="request" sourcevalue="" srcformatvalue="" target="request" targetdatatype="java.lang.String" testvalue="" value="">
            <accessType></accessType>
        </param>
        <param datatype="string" defaultvalue="" description="" encode="true" format="None" formatvalue="" name="TransferLocator" order="" paramOrder="16" parentOrder="-1" passnull="false" sms-name="" src="request" sourcevalue="" srcformatvalue="" target="request" targetdatatype="java.lang.String" testvalue="" value="">
            <accessType></accessType>
        </param>
        <param datatype="string" defaultvalue="" description="" encode="true" format="None" formatvalue="" name="transferId" order="" paramOrder="17" parentOrder="-1" passnull="false" sms-name="" src="request" sourcevalue="" srcformatvalue="" target="request" targetdatatype="java.lang.String" testvalue="" value="">
            <accessType></accessType>
        </param>
        <param datatype="string" defaultvalue="" description="" encode="true" format="None" formatvalue="" name="paymentId" order="" paramOrder="18" parentOrder="-1" passnull="false" sms-name="" src="request" sourcevalue="" srcformatvalue="" target="request" targetdatatype="java.lang.String" testvalue="" value="">
            <accessType></accessType>
        </param>
        <param datatype="string" defaultvalue="" description="" encode="true" format="None" formatvalue="" name="frequency" order="" paramOrder="19" parentOrder="-1" passnull="false" sms-name="" src="request" sourcevalue="" srcformatvalue="" target="request" targetdatatype="java.lang.String" testvalue="" value="">
            <accessType></accessType>
        </param>
        <param datatype="string" defaultvalue="" description="" encode="true" format="None" formatvalue="" name="processingDate" order="" paramOrder="20" parentOrder="-1" passnull="false" sms-name="" src="request" sourcevalue="" srcformatvalue="" target="request" targetdatatype="java.lang.String" testvalue="" value="">
            <accessType></accessType>
        </param>
        <param datatype="string" defaultvalue="" description="" encode="true" format="None" formatvalue="" name="numberOfPayments" order="" paramOrder="21" parentOrder="-1" passnull="false" sms-name="" src="request" sourcevalue="" srcformatvalue="" target="request" targetdatatype="java.lang.String" testvalue="" value="">
            <accessType></accessType>
        </param>
        <param datatype="string" defaultvalue="" description="" encode="true" format="None" formatvalue="" name="noofRecurrences" order="" paramOrder="22" parentOrder="-1" passnull="false" sms-name="" src="request" sourcevalue="" srcformatvalue="" target="request" targetdatatype="java.lang.String" testvalue="" value="">
            <accessType></accessType>
        </param>
        <param datatype="string" defaultvalue="" description="" encode="true" format="None" formatvalue="" name="accountCode" order="" paramOrder="23" parentOrder="-1" passnull="false" sms-name="" src="request" sourcevalue="" srcformatvalue="" target="request" targetdatatype="java.lang.String" testvalue="" value="">
            <accessType></accessType>
        </param>
        <param datatype="string" defaultvalue="" description="" encode="true" format="None" formatvalue="" name="validate" order="" paramOrder="24" parentOrder="-1" passnull="false" sms-name="" src="request" sourcevalue="" srcformatvalue="" target="request" targetdatatype="java.lang.String" testvalue="" value="">
            <accessType></accessType>
        </param>
        <param datatype="string" defaultvalue="" description="" encode="true" format="None" formatvalue="" name="uploadedattachments" order="" paramOrder="25" parentOrder="-1" passnull="false" sms-name="" src="request" sourcevalue="" srcformatvalue="" target="request" targetdatatype="java.lang.String" testvalue="" value="">
            <accessType></accessType>
        </param>
        <param datatype="string" defaultvalue="" description="" encode="true" format="None" formatvalue="" name="deletedDocuments" order="" paramOrder="26" parentOrder="-1" passnull="false" sms-name="" src="request" sourcevalue="" srcformatvalue="" target="request" targetdatatype="java.lang.String" testvalue="" value="">
            <accessType></accessType>
        </param>
        <param datatype="string" defaultvalue="" description="" encode="true" format="None" formatvalue="" name="swiftCode" order="" paramOrder="27" parentOrder="-1" passnull="false" sms-name="" src="request" sourcevalue="" srcformatvalue="" target="request" targetdatatype="java.lang.String" testvalue="" value="">
            <accessType></accessType>
        </param>
        <param datatype="string" defaultvalue="" description="" encode="true" format="None" formatvalue="" name="paidBy" order="" paramOrder="28" parentOrder="-1" passnull="false" sms-name="" src="request" sourcevalue="" srcformatvalue="" target="request" targetdatatype="java.lang.String" testvalue="" value="">
            <accessType></accessType>
        </param>
        <param datatype="string" defaultvalue="" description="" encode="true" format="None" formatvalue="" name="totalAmount" order="" paramOrder="29" parentOrder="-1" passnull="false" sms-name="" src="request" sourcevalue="" srcformatvalue="" target="request" targetdatatype="java.lang.String" testvalue="" value="">
            <accessType></accessType>
        </param>
        <param datatype="string" defaultvalue="" description="" encode="true" format="None" formatvalue="" name="creditValueDate" order="" paramOrder="30" parentOrder="-1" passnull="false" sms-name="" src="request" sourcevalue="" srcformatvalue="" target="request" targetdatatype="java.lang.String" testvalue="" value="">
            <accessType></accessType>
        </param>
        <param datatype="string" defaultvalue="" description="" encode="true" format="None" formatvalue="" name="exchangeRate" order="" paramOrder="31" parentOrder="-1" passnull="false" sms-name="" src="request" sourcevalue="" srcformatvalue="" target="request" targetdatatype="java.lang.String" testvalue="" value="">
            <accessType></accessType>
        </param>
        <param datatype="string" defaultvalue="" description="" encode="true" format="None" formatvalue="" name="charges" order="" paramOrder="32" parentOrder="-1" passnull="false" sms-name="" src="request" sourcevalue="" srcformatvalue="" target="request" targetdatatype="java.lang.String" testvalue="" value="">
            <accessType></accessType>
        </param>
    </service-input>
    <service-output passthrough="false">
        <dataset defaultvalue="" id="status" order="" paramOrder="8" parentOrder="0" src="" testvalue="">
            <param datatype="string" defaultvalue="" description="" encode="true" format="None" formatvalue="" name="creditValueDate" order="" paramOrder="71" parentOrder="8" passnull="false" sms-name="" src="" sourcevalue="" srcformatvalue="" target="response" targetdatatype="java.lang.String" testvalue="" value="">
                <accessType></accessType>
            </param>
            <param datatype="string" defaultvalue="" description="" encode="true" format="None" formatvalue="" name="totalAmount" order="" paramOrder="72" parentOrder="8" passnull="false" sms-name="" src="" sourcevalue="" srcformatvalue="" target="response" targetdatatype="java.lang.String" testvalue="" value="">
                <accessType></accessType>
            </param>
            <param datatype="string" defaultvalue="" description="" encode="true" format="None" formatvalue="" name="exchangeRate" order="" paramOrder="73" parentOrder="8" passnull="false" sms-name="" src="" sourcevalue="" srcformatvalue="" target="response" targetdatatype="java.lang.String" testvalue="" value="">
                <accessType></accessType>
            </param>
        </dataset>
        <dataset defaultvalue="" id="Transactions" order="" paramOrder="10" parentOrder="0" src="" testvalue="">
            <param datatype="string" defaultvalue="" description="" encode="true" format="None" formatvalue="" name="amount" order="" paramOrder="11" parentOrder="10" passnull="false" sms-name="" src="" sourcevalue="" srcformatvalue="" target="response" targetdatatype="java.lang.String" testvalue="" value="">
                <accessType></accessType>
            </param>
            <param datatype="string" defaultvalue="" description="" encode="true" format="None" formatvalue="" name="description" order="" paramOrder="12" parentOrder="10" passnull="false" sms-name="" src="" sourcevalue="" srcformatvalue="" target="response" targetdatatype="java.lang.String" testvalue="" value="">
                <accessType></accessType>
            </param>
            <param datatype="string" defaultvalue="" description="" encode="true" format="None" formatvalue="" name="fromAccountBalance" order="" paramOrder="13" parentOrder="10" passnull="false" sms-name="" src="" sourcevalue="" srcformatvalue="" target="response" targetdatatype="java.lang.String" testvalue="" value="">
                <accessType></accessType>
            </param>
            <param datatype="string" defaultvalue="" description="" encode="true" format="None" formatvalue="" name="fromAccountName" order="" paramOrder="14" parentOrder="10" passnull="false" sms-name="" src="" sourcevalue="" srcformatvalue="" target="response" targetdatatype="java.lang.String" testvalue="" value="">
                <accessType></accessType>
            </param>
            <param datatype="string" defaultvalue="" description="" encode="true" format="None" formatvalue="" name="fromAccountNumber" order="" paramOrder="15" parentOrder="10" passnull="false" sms-name="" src="" sourcevalue="" srcformatvalue="" target="response" targetdatatype="java.lang.String" testvalue="" value="">
                <accessType></accessType>
            </param>
            <param datatype="string" defaultvalue="" description="" encode="true" format="None" formatvalue="" name="hasDepositImage" order="" paramOrder="16" parentOrder="10" passnull="false" sms-name="" src="" sourcevalue="" srcformatvalue="" target="response" targetdatatype="java.lang.String" testvalue="" value="">
                <accessType></accessType>
            </param>
            <param datatype="string" defaultvalue="" description="" encode="true" format="None" formatvalue="" name="transactionId" order="" paramOrder="17" parentOrder="10" passnull="false" sms-name="" src="" sourcevalue="" srcformatvalue="" target="response" targetdatatype="java.lang.String" testvalue="" value="">
                <accessType></accessType>
            </param>
            <param datatype="string" defaultvalue="" description="" encode="true" format="None" formatvalue="" name="isScheduled" order="" paramOrder="18" parentOrder="10" passnull="false" sms-name="" src="" sourcevalue="" srcformatvalue="" target="response" targetdatatype="java.lang.String" testvalue="" value="">
                <accessType></accessType>
            </param>
            <param datatype="string" defaultvalue="" description="" encode="true" format="None" formatvalue="" name="toAccountName" order="" paramOrder="19" parentOrder="10" passnull="false" sms-name="" src="" sourcevalue="" srcformatvalue="" target="response" targetdatatype="java.lang.String" testvalue="" value="">
                <accessType></accessType>
            </param>
            <param datatype="string" defaultvalue="" description="" encode="true" format="None" formatvalue="" name="toAccountNumber" order="" paramOrder="20" parentOrder="10" passnull="false" sms-name="" src="" sourcevalue="" srcformatvalue="" target="response" targetdatatype="java.lang.String" testvalue="" value="">
                <accessType></accessType>
            </param>
            <param datatype="string" defaultvalue="" description="" encode="true" format="None" formatvalue="" name="transactiontype" order="" paramOrder="21" parentOrder="10" passnull="false" sms-name="" src="" sourcevalue="" srcformatvalue="" target="response" targetdatatype="java.lang.String" testvalue="" value="">
                <accessType></accessType>
            </param>
            <param datatype="string" defaultvalue="" description="" encode="true" format="None" formatvalue="" name="transactionDate" order="" paramOrder="22" parentOrder="10" passnull="false" sms-name="" src="" sourcevalue="" srcformatvalue="" target="response" targetdatatype="java.lang.String" testvalue="" value="">
                <accessType></accessType>
            </param>
            <param datatype="string" defaultvalue="" description="" encode="true" format="None" formatvalue="" name="payeeNickName" order="" paramOrder="23" parentOrder="10" passnull="false" sms-name="" src="" sourcevalue="" srcformatvalue="" target="response" targetdatatype="java.lang.String" testvalue="" value="">
                <accessType></accessType>
            </param>
            <param datatype="string" defaultvalue="" description="" encode="true" format="None" formatvalue="" name="scheduledDate" order="" paramOrder="24" parentOrder="10" passnull="false" sms-name="" src="" sourcevalue="" srcformatvalue="" target="response" targetdatatype="java.lang.String" testvalue="" value="">
                <accessType></accessType>
            </param>
            <param datatype="string" defaultvalue="" description="" encode="true" format="None" formatvalue="" name="fromAccountType" order="" paramOrder="25" parentOrder="10" passnull="false" sms-name="" src="" sourcevalue="" srcformatvalue="" target="response" targetdatatype="java.lang.String" testvalue="" value="">
                <accessType></accessType>
            </param>
            <param datatype="string" defaultvalue="" description="" encode="true" format="None" formatvalue="" name="transactionsNotes" order="" paramOrder="26" parentOrder="10" passnull="false" sms-name="" src="" sourcevalue="" srcformatvalue="" target="response" targetdatatype="java.lang.String" testvalue="" value="">
                <accessType></accessType>
            </param>
            <param datatype="string" defaultvalue="" description="" encode="true" format="None" formatvalue="" name="statusDescription" order="" paramOrder="27" parentOrder="10" passnull="false" sms-name="" src="" sourcevalue="" srcformatvalue="" target="response" targetdatatype="java.lang.String" testvalue="" value="">
                <accessType></accessType>
            </param>
            <param datatype="string" defaultvalue="" description="" encode="true" format="None" formatvalue="" name="transactionComments" order="" paramOrder="28" parentOrder="10" passnull="false" sms-name="" src="" sourcevalue="" srcformatvalue="" target="response" targetdatatype="java.lang.String" testvalue="" value="">
                <accessType></accessType>
            </param>
            <param datatype="string" defaultvalue="" description="" encode="true" format="None" formatvalue="" name="toAccountType" order="" paramOrder="29" parentOrder="10" passnull="false" sms-name="" src="" sourcevalue="" srcformatvalue="" target="response" targetdatatype="java.lang.String" testvalue="" value="">
                <accessType></accessType>
            </param>
            <param datatype="string" defaultvalue="" description="" encode="true" format="None" formatvalue="" name="ExternalAccountNumber" order="" paramOrder="30" parentOrder="10" passnull="false" sms-name="" src="" sourcevalue="" srcformatvalue="" target="response" targetdatatype="java.lang.String" testvalue="" value="">
                <accessType></accessType>
            </param>
            <param datatype="string" defaultvalue="" description="" encode="true" format="None" formatvalue="" name="payPersonName" order="" paramOrder="31" parentOrder="10" passnull="false" sms-name="" src="" sourcevalue="" srcformatvalue="" target="response" targetdatatype="java.lang.String" testvalue="" value="">
                <accessType></accessType>
            </param>
            <param datatype="string" defaultvalue="" description="" encode="true" format="None" formatvalue="" name="payPersonEmail" order="" paramOrder="32" parentOrder="10" passnull="false" sms-name="" src="" sourcevalue="" srcformatvalue="" target="response" targetdatatype="java.lang.String" testvalue="" value="">
                <accessType></accessType>
            </param>
            <param datatype="string" defaultvalue="" description="" encode="true" format="None" formatvalue="" name="payeeId" order="" paramOrder="33" parentOrder="10" passnull="false" sms-name="" src="" sourcevalue="" srcformatvalue="" target="response" targetdatatype="java.lang.String" testvalue="" value="">
                <accessType></accessType>
            </param>
            <param datatype="string" defaultvalue="" description="" encode="true" format="None" formatvalue="" name="frequencyType" order="" paramOrder="34" parentOrder="10" passnull="false" sms-name="" src="" sourcevalue="" srcformatvalue="" target="response" targetdatatype="java.lang.String" testvalue="" value="">
                <accessType></accessType>
            </param>
            <param datatype="string" defaultvalue="" description="" encode="true" format="None" formatvalue="" name="numberOfRecurrences" order="" paramOrder="35" parentOrder="10" passnull="false" sms-name="" src="" sourcevalue="" srcformatvalue="" target="response" targetdatatype="java.lang.String" testvalue="" value="">
                <accessType></accessType>
            </param>
            <param datatype="string" defaultvalue="" description="" encode="true" format="None" formatvalue="" name="frequencyStartDate" order="" paramOrder="36" parentOrder="10" passnull="false" sms-name="" src="" sourcevalue="" srcformatvalue="" target="response" targetdatatype="java.lang.String" testvalue="" value="">
                <accessType></accessType>
            </param>
            <param datatype="string" defaultvalue="" description="" encode="true" format="None" formatvalue="" name="frequencyEndDate" order="" paramOrder="37" parentOrder="10" passnull="false" sms-name="" src="" sourcevalue="" srcformatvalue="" target="response" targetdatatype="java.lang.String" testvalue="" value="">
                <accessType></accessType>
            </param>
            <param datatype="string" defaultvalue="" description="" encode="true" format="None" formatvalue="" name="fromNickName" order="" paramOrder="38" parentOrder="10" passnull="false" sms-name="" src="" sourcevalue="" srcformatvalue="" target="response" targetdatatype="java.lang.String" testvalue="" value="">
                <accessType></accessType>
            </param>
            <param datatype="string" defaultvalue="" description="" encode="true" format="None" formatvalue="" name="cashlessMode" order="" paramOrder="39" parentOrder="10" passnull="false" sms-name="" src="" sourcevalue="" srcformatvalue="" target="response" targetdatatype="java.lang.String" testvalue="" value="">
                <accessType></accessType>
            </param>
            <param datatype="string" defaultvalue="" description="" encode="true" format="None" formatvalue="" name="cashlessPersonName" order="" paramOrder="40" parentOrder="10" passnull="false" sms-name="" src="" sourcevalue="" srcformatvalue="" target="response" targetdatatype="java.lang.String" testvalue="" value="">
                <accessType></accessType>
            </param>
            <param datatype="string" defaultvalue="" description="" encode="true" format="None" formatvalue="" name="cashWithdrawalTransactionStatus" order="" paramOrder="41" parentOrder="10" passnull="false" sms-name="" src="" sourcevalue="" srcformatvalue="" target="response" targetdatatype="java.lang.String" testvalue="" value="">
                <accessType></accessType>
            </param>
            <param datatype="string" defaultvalue="" description="" encode="true" format="None" formatvalue="" name="cashlessSecurityCode" order="" paramOrder="42" parentOrder="10" passnull="false" sms-name="" src="" sourcevalue="" srcformatvalue="" target="response" targetdatatype="java.lang.String" testvalue="" value="">
                <accessType></accessType>
            </param>
            <param datatype="string" defaultvalue="" description="" encode="true" format="None" formatvalue="" name="cashlessEmail" order="" paramOrder="43" parentOrder="10" passnull="false" sms-name="" src="" sourcevalue="" srcformatvalue="" target="response" targetdatatype="java.lang.String" testvalue="" value="">
                <accessType></accessType>
            </param>
            <param datatype="string" defaultvalue="" description="" encode="true" format="None" formatvalue="" name="cashlessPhone" order="" paramOrder="44" parentOrder="10" passnull="false" sms-name="" src="" sourcevalue="" srcformatvalue="" target="response" targetdatatype="java.lang.String" testvalue="" value="">
                <accessType></accessType>
            </param>
            <param datatype="string" defaultvalue="" description="" encode="true" format="None" formatvalue="" name="cashlessOTP" order="" paramOrder="45" parentOrder="10" passnull="false" sms-name="" src="" sourcevalue="" srcformatvalue="" target="response" targetdatatype="java.lang.String" testvalue="" value="">
                <accessType></accessType>
            </param>
            <param datatype="string" defaultvalue="" description="" encode="true" format="None" formatvalue="" name="cashlessOTPValidDate" order="" paramOrder="46" parentOrder="10" passnull="false" sms-name="" src="" sourcevalue="" srcformatvalue="" target="response" targetdatatype="java.lang.String" testvalue="" value="">
                <accessType></accessType>
            </param>
            <param datatype="string" defaultvalue="" description="" encode="true" format="None" formatvalue="" name="category" order="" paramOrder="47" parentOrder="10" passnull="false" sms-name="" src="" sourcevalue="" srcformatvalue="" target="response" targetdatatype="java.lang.String" testvalue="" value="">
                <accessType></accessType>
            </param>
            <param datatype="string" defaultvalue="" description="" encode="true" format="None" formatvalue="" name="recurrenceDesc" order="" paramOrder="48" parentOrder="10" passnull="false" sms-name="" src="" sourcevalue="" srcformatvalue="" target="response" targetdatatype="java.lang.String" testvalue="" value="">
                <accessType></accessType>
            </param>
            <param datatype="string" defaultvalue="" description="" encode="true" format="None" formatvalue="" name="viewReportLink" order="" paramOrder="49" parentOrder="10" passnull="false" sms-name="" src="" sourcevalue="" srcformatvalue="" target="response" targetdatatype="java.lang.String" testvalue="" value="">
                <accessType></accessType>
            </param>
            <param datatype="string" defaultvalue="" description="" encode="true" format="None" formatvalue="" name="linkSelf" order="" paramOrder="50" parentOrder="10" passnull="false" sms-name="" src="" sourcevalue="" srcformatvalue="" target="response" targetdatatype="java.lang.String" testvalue="" value="">
                <accessType></accessType>
            </param>
            <param datatype="string" defaultvalue="" description="" encode="true" format="None" formatvalue="" name="createdDate" order="" paramOrder="51" parentOrder="10" passnull="false" sms-name="" src="" sourcevalue="" srcformatvalue="" target="response" targetdatatype="java.lang.String" testvalue="" value="">
                <accessType></accessType>
            </param>
            <param datatype="string" defaultvalue="" description="" encode="true" format="None" formatvalue="" name="StatusUpdateDateTime" order="" paramOrder="52" parentOrder="10" passnull="false" sms-name="" src="" sourcevalue="" srcformatvalue="" target="response" targetdatatype="java.lang.String" testvalue="" value="">
                <accessType></accessType>
            </param>
            <param datatype="string" defaultvalue="" description="" encode="true" format="None" formatvalue="" name="DomesticPaymentId" order="" paramOrder="53" parentOrder="10" passnull="false" sms-name="" src="" sourcevalue="" srcformatvalue="" target="response" targetdatatype="java.lang.String" testvalue="" value="">
                <accessType></accessType>
            </param>
            <param datatype="string" defaultvalue="" description="" encode="true" format="None" formatvalue="" name="dataStatus" order="" paramOrder="54" parentOrder="10" passnull="false" sms-name="" src="" sourcevalue="" srcformatvalue="" target="response" targetdatatype="java.lang.String" testvalue="" value="">
                <accessType></accessType>
            </param>
            <param datatype="string" defaultvalue="" description="" encode="true" format="None" formatvalue="" name="ConsentId" order="" paramOrder="55" parentOrder="10" passnull="false" sms-name="" src="" sourcevalue="" srcformatvalue="" target="response" targetdatatype="java.lang.String" testvalue="" value="">
                <accessType></accessType>
            </param>
            <param datatype="string" defaultvalue="" description="" encode="true" format="None" formatvalue="" name="Initiation_InstructionIdentification" order="" paramOrder="56" parentOrder="10" passnull="false" sms-name="" src="" sourcevalue="" srcformatvalue="" target="response" targetdatatype="java.lang.String" testvalue="" value="">
                <accessType></accessType>
            </param>
            <param datatype="string" defaultvalue="" description="" encode="true" format="None" formatvalue="" name="debtorAccountName" order="" paramOrder="57" parentOrder="10" passnull="false" sms-name="" src="" sourcevalue="" srcformatvalue="" target="response" targetdatatype="java.lang.String" testvalue="" value="">
                <accessType></accessType>
            </param>
            <param datatype="string" defaultvalue="" description="" encode="true" format="None" formatvalue="" name="creditorAccountSchemeName" order="" paramOrder="58" parentOrder="10" passnull="false" sms-name="" src="" sourcevalue="" srcformatvalue="" target="response" targetdatatype="java.lang.String" testvalue="" value="">
                <accessType></accessType>
            </param>
            <param datatype="string" defaultvalue="" description="" encode="true" format="None" formatvalue="" name="RI_Unstructured" order="" paramOrder="59" parentOrder="10" passnull="false" sms-name="" src="" sourcevalue="" srcformatvalue="" target="response" targetdatatype="java.lang.String" testvalue="" value="">
                <accessType></accessType>
            </param>
            <param datatype="string" defaultvalue="" description="" encode="true" format="None" formatvalue="" name="RI_Reference" order="" paramOrder="60" parentOrder="10" passnull="false" sms-name="" src="" sourcevalue="" srcformatvalue="" target="response" targetdatatype="java.lang.String" testvalue="" value="">
                <accessType></accessType>
            </param>
            <param datatype="string" defaultvalue="" description="" encode="true" format="None" formatvalue="" name="Initiation_EndToEndIdentification" order="" paramOrder="61" parentOrder="10" passnull="false" sms-name="" src="" sourcevalue="" srcformatvalue="" target="response" targetdatatype="java.lang.String" testvalue="" value="">
                <accessType></accessType>
            </param>
            <param datatype="string" defaultvalue="" description="" encode="true" format="None" formatvalue="" name="RiskPaymentContextCode" order="" paramOrder="62" parentOrder="10" passnull="false" sms-name="" src="" sourcevalue="" srcformatvalue="" target="response" targetdatatype="java.lang.String" testvalue="" value="">
                <accessType></accessType>
            </param>
            <param datatype="string" defaultvalue="" description="" encode="true" format="None" formatvalue="" name="backendReferenceId" order="" paramOrder="63" parentOrder="10" passnull="false" sms-name="" src="" sourcevalue="" srcformatvalue="" target="response" targetdatatype="java.lang.String" testvalue="" value="">
                <accessType></accessType>
            </param>
            <param datatype="string" defaultvalue="" description="" encode="true" format="None" formatvalue="" name="serviceCharge" order="" paramOrder="64" parentOrder="10" passnull="false" sms-name="" src="" sourcevalue="" srcformatvalue="" target="response" targetdatatype="java.lang.String" testvalue="" value="">
                <accessType></accessType>
            </param>
            <param datatype="string" defaultvalue="" description="" encode="true" format="None" formatvalue="" name="transactionAmount" order="" paramOrder="66" parentOrder="10" passnull="false" sms-name="" src="" sourcevalue="" srcformatvalue="" target="response" targetdatatype="java.lang.String" testvalue="" value="">
                <accessType></accessType>
            </param>
            <param datatype="string" defaultvalue="" description="" encode="true" format="None" formatvalue="" name="convertedAmount" order="" paramOrder="68" parentOrder="10" passnull="false" sms-name="" src="" sourcevalue="" srcformatvalue="" target="response" targetdatatype="java.lang.String" testvalue="" value="">
                <accessType></accessType>
            </param>
        </dataset>
        <param datatype="string" defaultvalue="" description="" encode="true" format="None" formatvalue="" name="errmsg" order="" paramOrder="1" parentOrder="0" passnull="false" sms-name="" src="" sourcevalue="" srcformatvalue="" target="response" targetdatatype="java.lang.String" testvalue="" value="">
            <accessType></accessType>
        </param>
        <param datatype="string" defaultvalue="" description="" encode="true" format="None" formatvalue="" name="success" order="" paramOrder="2" parentOrder="0" passnull="false" sms-name="" src="" sourcevalue="" srcformatvalue="" target="response" targetdatatype="java.lang.String" testvalue="" value="">
            <accessType></accessType>
        </param>
        <param datatype="string" defaultvalue="" description="" encode="true" format="None" formatvalue="" name="referenceId" order="" paramOrder="3" parentOrder="0" passnull="false" sms-name="" src="" sourcevalue="" srcformatvalue="" target="response" targetdatatype="java.lang.String" testvalue="" value="">
            <accessType></accessType>
        </param>
        <param datatype="string" defaultvalue="" description="" encode="true" format="None" formatvalue="" name="otp" order="" paramOrder="4" parentOrder="0" passnull="false" sms-name="" src="" sourcevalue="" srcformatvalue="" target="response" targetdatatype="java.lang.String" testvalue="" value="">
            <accessType></accessType>
        </param>
        <param datatype="string" defaultvalue="" description="" encode="true" format="None" formatvalue="" name="validDate" order="" paramOrder="5" parentOrder="0" passnull="false" sms-name="" src="" sourcevalue="" srcformatvalue="" target="response" targetdatatype="java.lang.String" testvalue="" value="">
            <accessType></accessType>
        </param>
        <param datatype="string" defaultvalue="" description="" encode="true" format="None" formatvalue="" name="cashlessPersonName" order="" paramOrder="6" parentOrder="0" passnull="false" sms-name="" src="" sourcevalue="" srcformatvalue="" target="response" targetdatatype="java.lang.String" testvalue="" value="">
            <accessType></accessType>
        </param>
        <param datatype="string" defaultvalue="" description="" encode="true" format="None" formatvalue="" name="MFAAttributes" order="" paramOrder="7" parentOrder="0" passnull="false" sms-name="" src="" sourcevalue="" srcformatvalue="" target="response" targetdatatype="java.lang.String" testvalue="" value="">
            <accessType></accessType>
        </param>
        <param datatype="string" defaultvalue="" description="" encode="true" format="None" formatvalue="" name="message" order="" paramOrder="9" parentOrder="0" passnull="false" sms-name="" src="" sourcevalue="" srcformatvalue="" target="response" targetdatatype="java.lang.String" testvalue="" value="">
            <accessType></accessType>
        </param>
        <param datatype="string" defaultvalue="" description="" encode="true" format="None" formatvalue="" name="successfulUploads" order="" paramOrder="65" parentOrder="0" passnull="false" sms-name="" src="" sourcevalue="" srcformatvalue="" target="response" targetdatatype="java.lang.String" testvalue="" value="">
            <accessType></accessType>
        </param>
        <param datatype="string" defaultvalue="" description="" encode="true" format="None" formatvalue="" name="failedUploads" order="" paramOrder="67" parentOrder="0" passnull="false" sms-name="" src="" sourcevalue="" srcformatvalue="" target="response" targetdatatype="java.lang.String" testvalue="" value="">
            <accessType></accessType>
        </param>
        <param datatype="string" defaultvalue="" description="" encode="true" format="None" formatvalue="" name="swiftCode" order="" paramOrder="69" parentOrder="0" passnull="false" sms-name="" src="" sourcevalue="" srcformatvalue="" target="response" targetdatatype="java.lang.String" testvalue="" value="">
            <accessType></accessType>
        </param>
        <param datatype="string" defaultvalue="" description="" encode="true" format="None" formatvalue="" name="paidBy" order="" paramOrder="70" parentOrder="0" passnull="false" sms-name="" src="" sourcevalue="" srcformatvalue="" target="response" targetdatatype="java.lang.String" testvalue="" value="">
            <accessType></accessType>
        </param>
    </service-output>
</service>
