<?xml version="1.0" encoding="UTF-8" standalone="yes"?>
<service serviceGroup="" cachable="false" cacheduration="" description="" endpoint="default" groupType="" id="getLoanDetails" passwordencrypted="false" security="authorized_app_user" type="jsonConnector" smscode="" smsenabled="false">
    <service-config>
        <config-param api-version="" appid="" name="preprocessorname" value=""/>
        <config-param api-version="" appid="" name="postprocessorname" value="com.infinity.dbx.temenos.accounts.LoanAccountDetailsPostProcessor"/>
        <config-param api-version="" appid="" name="preprocessorJS" value=""/>
        <config-param api-version="" appid="" name="postprocessorJS" value=""/>
        <config-param api-version="" appid="" name="preprocessorRules" value=""/>
        <config-param api-version="" appid="" name="postprocessorRules" value=""/>
        <config-param api-version="" appid="" name="kony_http_supported_methods" value="POST"/>
        <config-param api-version="" appid="" name="endpointUrl" value="https://_$_T24_ACCOUNTS_HOST_URL_$_/v1.1.0/holdings/loans/$accountID?dateFrom=$dateFrom"/>
        <config-param api-version="" appid="" name="ignorehttpproxy" value="true"/>
        <config-param api-version="" appid="" name="http.method" value="GET"/>
        <config-param api-version="" appid="" name="dataObjectName" value=""/>
        <config-param api-version="" appid="" name="sockettimeout" value=""/>
        <config-param api-version="" appid="" name="responseEncoding" value="UTF-8"/>
        <config-param api-version="" appid="" name="isembedxmlpresent" value="false"/>
        <config-param api-version="" appid="" name="retrycount" value="0"/>
        <config-param api-version="" appid="" name="urlprovider" value="com.kony.dbx.util.ServiceURLProvider"/>
        <config-param api-version="" appid="" name="identityProvider" value="DbxUserLogin"/>
        <config-param api-version="" appid="" name="identityProviderType" value="custom"/>
    </service-config>
    <service-input passthrough="false">
        <header datatype="" name="" passthrough="false">
            <param datatype="string" defaultvalue="" description="" encode="false" format="None" formatvalue="" name="Authorization" order="" paramOrder="0" parentOrder="0" sms-name="" src="request" sourcevalue="" srcformatvalue="" target="" targetdatatype="" testvalue="" value="">
                <accessType></accessType>
            </param>
            <param datatype="string" defaultvalue="" description="" encode="false" format="None" formatvalue="" name="companyId" order="" paramOrder="0" parentOrder="0" sms-name="" src="identity" sourcevalue="DbxUserLogin.profile.companyId" srcformatvalue="" target="" targetdatatype="" testvalue="" value="">
                <accessType></accessType>
            </param>
        </header>
        <param datatype="string" defaultvalue="" description="" encode="true" format="None" formatvalue="" name="accountID" order="" paramOrder="1" parentOrder="-1" passnull="false" sms-name="" src="request" sourcevalue="" srcformatvalue="" target="request" targetdatatype="java.lang.String" testvalue="" value="">
            <accessType></accessType>
        </param>
        <param datatype="string" defaultvalue="" description="" encode="true" format="None" formatvalue="" name="coreIdentifier" order="" paramOrder="2" parentOrder="-1" passnull="false" sms-name="" src="identity" sourcevalue="DbxUserLogin.profile.backendIdentifiers" srcformatvalue="" target="identity" targetdatatype="java.lang.String" testvalue="" value="">
            <accessType></accessType>
        </param>
        <param datatype="string" defaultvalue="" description="" encode="true" format="None" formatvalue="" name="dateFrom" order="" paramOrder="3" parentOrder="-1" passnull="false" sms-name="" src="request" sourcevalue="" srcformatvalue="" target="request" targetdatatype="java.lang.String" testvalue="" value="">
            <accessType></accessType>
        </param>
        <stub-param value=""/>
    </service-input>
    <service-output passthrough="false">
        <dataset defaultvalue="" id="interests" order="" paramOrder="8" parentOrder="0" src="//interests" testvalue="">
            <param datatype="number" defaultvalue="" description="" encode="true" format="None" formatvalue="" name="dividentPaidYtd" order="" paramOrder="6" parentOrder="8" passnull="false" sms-name="" src="dividentPaidYtd" sourcevalue="" srcformatvalue="" target="response" targetdatatype="java.lang.String" testvalue="" value="">
                <accessType></accessType>
            </param>
        </dataset>
        <dataset defaultvalue="" id="schedules" order="" paramOrder="13" parentOrder="0" src="//schedules" testvalue="">
            <param datatype="string" defaultvalue="" description="" encode="true" format="None" formatvalue="" name="futureScheduleCount" order="" paramOrder="14" parentOrder="13" passnull="false" sms-name="" src="futureScheduleCount" sourcevalue="" srcformatvalue="" target="response" targetdatatype="java.lang.String" testvalue="" value="">
                <accessType></accessType>
            </param>
            <param datatype="string" defaultvalue="" description="" encode="true" format="None" formatvalue="" name="paidScheduleCount" order="" paramOrder="15" parentOrder="13" passnull="false" sms-name="" src="paidScheduleCount" sourcevalue="" srcformatvalue="" target="response" targetdatatype="java.lang.String" testvalue="" value="">
                <accessType></accessType>
            </param>
            <param datatype="string" defaultvalue="" description="" encode="true" format="None" formatvalue="" name="dueScheduleCount" order="" paramOrder="16" parentOrder="13" passnull="false" sms-name="" src="dueScheduleCount" sourcevalue="" srcformatvalue="" target="response" targetdatatype="java.lang.String" testvalue="" value="">
                <accessType></accessType>
            </param>
            <param datatype="string" defaultvalue="" description="" encode="true" format="None" formatvalue="" name="scheduleProperty" order="" paramOrder="18" parentOrder="13" passnull="false" sms-name="" src="scheduleProperty" sourcevalue="" srcformatvalue="" target="response" targetdatatype="java.lang.String" testvalue="" value="">
                <accessType></accessType>
            </param>
            <param datatype="string" defaultvalue="" description="" encode="true" format="None" formatvalue="" name="schedulePaymentFrequency" order="" paramOrder="19" parentOrder="13" passnull="false" sms-name="" src="schedulePaymentFrequency" sourcevalue="" srcformatvalue="" target="response" targetdatatype="java.lang.String" testvalue="" value="">
                <accessType></accessType>
            </param>
        </dataset>
        <param datatype="string" defaultvalue="" description="" encode="true" format="None" formatvalue="" name="lastPaymentDate" order="" paramOrder="1" parentOrder="0" passnull="false" sms-name="" src="//lastPaidDate" sourcevalue="" srcformatvalue="" target="response" targetdatatype="java.lang.String" testvalue="" value="">
            <accessType></accessType>
        </param>
        <param datatype="string" defaultvalue="" description="" encode="true" format="None" formatvalue="" name="interestRate" order="" paramOrder="2" parentOrder="0" passnull="false" sms-name="" src="//interestRate" sourcevalue="" srcformatvalue="" target="response" targetdatatype="java.lang.String" testvalue="" value="">
            <accessType></accessType>
        </param>
        <param datatype="number" defaultvalue="" description="" encode="true" format="None" formatvalue="" name="originalAmount" order="" paramOrder="3" parentOrder="0" passnull="false" sms-name="" src="//commitmentBalance" sourcevalue="" srcformatvalue="" target="response" targetdatatype="java.lang.String" testvalue="" value="">
            <accessType></accessType>
        </param>
        <param datatype="string" defaultvalue="" description="" encode="true" format="None" formatvalue="" name="currentAmountDue" order="" paramOrder="4" parentOrder="0" passnull="false" sms-name="" src="//totalDueAmount" sourcevalue="" srcformatvalue="" target="response" targetdatatype="java.lang.String" testvalue="" value="">
            <accessType></accessType>
        </param>
        <param datatype="string" defaultvalue="" description="" encode="true" format="None" formatvalue="" name="maturityDate" order="" paramOrder="5" parentOrder="0" passnull="false" sms-name="" src="//maturityDate" sourcevalue="" srcformatvalue="" target="response" targetdatatype="java.lang.String" testvalue="" value="">
            <accessType></accessType>
        </param>
        <param datatype="string" defaultvalue="" description="" encode="true" format="None" formatvalue="" name="lastPaymentAmount" order="" paramOrder="7" parentOrder="0" passnull="false" sms-name="" src="//lastPaidAmount" sourcevalue="" srcformatvalue="" target="response" targetdatatype="java.lang.String" testvalue="" value="">
            <accessType></accessType>
        </param>
        <param datatype="string" defaultvalue="" description="" encode="true" format="None" formatvalue="" name="accountHolder" order="" paramOrder="9" parentOrder="0" passnull="false" sms-name="" src="//customerName" sourcevalue="" srcformatvalue="" target="response" targetdatatype="java.lang.String" testvalue="" value="">
            <accessType></accessType>
        </param>
        <param datatype="string" defaultvalue="" description="" encode="true" format="None" formatvalue="" name="jointHolders" order="" paramOrder="10" parentOrder="0" passnull="false" sms-name="" src="//jointCustomerName" sourcevalue="" srcformatvalue="" target="response" targetdatatype="java.lang.String" testvalue="" value="">
            <accessType></accessType>
        </param>
        <param datatype="string" defaultvalue="" description="" encode="true" format="None" formatvalue="" name="nextPaymentDate" order="" paramOrder="11" parentOrder="0" passnull="false" sms-name="" src="//nextPaymentDate" sourcevalue="" srcformatvalue="" target="response" targetdatatype="java.lang.String" testvalue="" value="">
            <accessType></accessType>
        </param>
        <param datatype="string" defaultvalue="" description="" encode="true" format="None" formatvalue="" name="nextPaymentAmount" order="" paramOrder="12" parentOrder="0" passnull="false" sms-name="" src="//nextPaymentAmount" sourcevalue="" srcformatvalue="" target="response" targetdatatype="java.lang.String" testvalue="" value="">
            <accessType></accessType>
        </param>
        <param datatype="string" defaultvalue="" description="" encode="true" format="None" formatvalue="" name="startDate" order="" paramOrder="17" parentOrder="0" passnull="false" sms-name="" src="//startDate" sourcevalue="" srcformatvalue="" target="response" targetdatatype="java.lang.String" testvalue="" value="">
            <accessType></accessType>
        </param>
    </service-output>
</service>
