{
    "DNDConfig": null,
    "_height_": {
        "type": "string",
        "value": "46%"
    },
    "_left_": {
        "type": "string",
        "value": "0"
    },
    "_margin_": [
        0,
        0,
        0,
        0
    ],
    "_orientation_": 6,
    "_padding_": [
        0,
        0,
        0,
        0
    ],
    "_percent_": true,
    "_skin_": "sc22cacd2fce421cbc83a641d7fc8416",
    "_top_": {
        "type": "string",
        "value": "0"
    },
    "_width_": {
        "type": "string",
        "value": "90%"
    },
    "allboxes": [],
    "autogrowmode": 0,
    "canUpdateUI": true,
    "centerx": {
        "type": "string",
        "value": "50%"
    },
    "children": [
        "CopylblApproachesHeaderSF0dfea64a36b5148"
    ],
    "clipbounds": true,
    "containerweight": 100,
    "enablescrolling": true,
    "id": "CopyflxHeaderApproachesSF0ce8179f423a74a",
    "info": null,
    "iscustomlayout": false,
    "isvisible": true,
    "kuid": "i24988af9d4f4c1ead354d5085f71cf2",
    "layouttype": 2,
    "name": "kony.ui.FlexContainer",
    "parent": "CopyflxApproachRequestSF0bceae0ee10dd46",
    "pf": "frmInsightSF",
    "retaincontentalignment": false,
    "retainflexpositionproperties": false,
    "retainflowhorizontalalignment": false,
    "snapgridsize": 10,
    "snaptogrid": true,
    "wType": "FlexContainer",
    "widgetalignment": 1
}